{
  "tracks": [
    {
      "id": "xnP7qKxwzjg",
      "title": "Dracula (Official Video)",
      "artist": "Tame Impala",
      "duration_ms": 233361
    },
    {
      "id": "NMRhx71bGo4",
      "title": "Let It Happen",
      "artist": "Tame Impala",
      "duration_ms": 467601
    },
    {
      "id": "q5go1dovoeM",
      "title": "Money",
      "artist": "The Drums",
      "duration_ms": 234000
    },
    {
      "id": "NMRhx71bGo4",
      "title": "Let It Happen",
      "artist": "Tame Impala",
      "duration_ms": 468000
    },
    {
      "id": "7374CZQoS2Y",
      "title": "No Surprises (Remastered)",
      "artist": "Radiohead",
      "duration_ms": 229000
    },
    {
      "id": "MJDn70jh1V0",
      "title": "Hollow Knight OST - City of Tears",
      "artist": "Amellifera",
      "duration_ms": 179000
    },
    {
      "id": "gbSFZxq7hIQ",
      "title": "Let Down 9.1",
      "artist": "muvii",
      "duration_ms": 326000
    },
    {
      "id": "zkU5JYX-bIc",
      "title": "Introduction to the Snow",
      "artist": "ミラクルミュージカル",
      "duration_ms": 102000
    },
    {
      "id": "uxyM7vhU0uU",
      "title": "Dream Sweet in Sea Major",
      "artist": "ミラクルミュージカル",
      "duration_ms": 421000
    },
    {
      "id": "S4usqxibW88",
      "title": "Dark Is The Night (Remix)",
      "artist": "Luke Muzzic",
      "duration_ms": 183000
    },
    {
      "id": "7iDfvoqOhD8",
      "title": "Hallelujah",
      "artist": "Rufus Wainwright",
      "duration_ms": 249000
    },
    {
      "id": "6N2b14J-5tA",
      "title": "Take Me Home, Country Roads",
      "artist": "John Denver",
      "duration_ms": 198000
    },
    {
      "id": "-UbpcAqRowU",
      "title": "Killing Me Softly with Her Song",
      "artist": "Perry Como",
      "duration_ms": 272000
    },
    {
      "id": "YRkWZO4iLYk",
      "title": "Another Love",
      "artist": "Tom Odell",
      "duration_ms": 251000
    },
    {
      "id": "ZVgHPSyEIqk",
      "title": "Let Down (Remastered)",
      "artist": "Radiohead",
      "duration_ms": 300000
    },
    {
      "id": "W2o_HupXq1g",
      "title": "Golden Brown",
      "artist": "stranglersofficial",
      "duration_ms": 207000
    },
    {
      "id": "AMCwYdTJ_PE",
      "title": "Mask Off",
      "artist": "Future",
      "duration_ms": 205000
    },
    {
      "id": "IxJjY5T9yag",
      "title": "The Box",
      "artist": "Roddy Ricch",
      "duration_ms": 197000
    },
    {
      "id": "FJvCcnnW9iA",
      "title": "clair obscur: expedition 33 but it's western.",
      "artist": "Vivintinn",
      "duration_ms": 229000
    },
    {
      "id": "uV_5eEvamoQ",
      "title": "golden hour",
      "artist": "JVKE",
      "duration_ms": 210000
    },
    {
      "id": "sOv0hENoQnE",
      "title": "Soldier, Poet, King",
      "artist": "The Oh Hellos",
      "duration_ms": 166000
    },
    {
      "id": "6bGmUTAfh-A",
      "title": "Let Her Go",
      "artist": "Passenger",
      "duration_ms": 253000
    },
    {
      "id": "06ht9MyJLT4",
      "title": "Running With The Wolves",
      "artist": "AURORA",
      "duration_ms": 219000
    },
    {
      "id": "d_HlPboLRL8",
      "title": "Runaway",
      "artist": "AURORA",
      "duration_ms": 250000
    },
    {
      "id": "hqvcww4ydh8",
      "title": "Can't Tell Me Nothing",
      "artist": "Kanye West",
      "duration_ms": 272000
    },
    {
      "id": "gLBoyzFnAdE",
      "title": "Haule Haule",
      "artist": "Sukhwinder Singh - Official",
      "duration_ms": 264000
    },
    {
      "id": "AQ5qWopu_uU",
      "title": "Sajdaa (From \"My Name Is Khan\")",
      "artist": "Shankar Ehsaan Loy",
      "duration_ms": 366000
    },
    {
      "id": "_IjmfnOUqHs",
      "title": "BHAR DO JHOLI MERI (TRADITIONAL) W-IN",
      "artist": "Adnan Sami",
      "duration_ms": 500000
    },
    {
      "id": "XhYEe33MGfA",
      "title": "California Dreamin'",
      "artist": "Release",
      "duration_ms": 163000
    },
    {
      "id": "CtWxcA0ODX8",
      "title": "Against The Tide (The Captain's Tarantella)",
      "artist": "Sail North",
      "duration_ms": 170000
    },
    {
      "id": "QhC8iKOmvgY",
      "title": "Difyrrwch",
      "artist": "The Trials of Cato",
      "duration_ms": 182000
    },
    {
      "id": "hrH6mK0QYUw",
      "title": "Breathless - Shankar Mahadevan || Part - 2",
      "artist": "Entertainer Club",
      "duration_ms": 178000
    },
    {
      "id": "VBO36qyZx54",
      "title": "Teri Dastaan",
      "artist": "Jasleen Royal",
      "duration_ms": 224000
    },
    {
      "id": "3R-q79a7n98",
      "title": "Teri Deewani",
      "artist": "Kailash Kher",
      "duration_ms": 324000
    },
    {
      "id": "iP6ZABrm8Lo",
      "title": "Theme of Mitsuha",
      "artist": "RADWIMPS",
      "duration_ms": 247000
    },
    {
      "id": "CCcclu-gyIo",
      "title": "Theme of Ms. Okudera",
      "artist": "RADWIMPS",
      "duration_ms": 128000
    },
    {
      "id": "mpR0YIrvV7M",
      "title": "Thrift Shop (feat. Wanz)",
      "artist": "Macklemore",
      "duration_ms": 236000
    },
    {
      "id": "gnrSpwb2Ax4",
      "title": "Time in a Bottle",
      "artist": "Jim Croce",
      "duration_ms": 149000
    },
    {
      "id": "HFVM4QE1qBA",
      "title": "To Ashes and Blood (from the series Arcane League of Legends)",
      "artist": "WOODKID",
      "duration_ms": 246000
    },
    {
      "id": "grSRDyV8Ge8",
      "title": "Tomake Chuye Dilam (Female Version)",
      "artist": "Shreya Ghoshal Official",
      "duration_ms": 348000
    },
    {
      "id": "8iyJXi3yA1c",
      "title": "Tomake Chai (Female)",
      "artist": "Madhubanti Bagchi",
      "duration_ms": 247000
    },
    {
      "id": "PW6SfNsYjXs",
      "title": "Tomake Chuye Dilam (Male Version)",
      "artist": "Arijit Singh",
      "duration_ms": 348000
    },
    {
      "id": "DVByO8nBUH0",
      "title": "Tomar Chokher Shitolpati",
      "artist": "Lagnajita Chakraborty",
      "duration_ms": 242000
    },
    {
      "id": "CaY9TzCUuJs",
      "title": "Tomaro awsheeme",
      "artist": "Piya Chakraborty",
      "duration_ms": 323000
    },
    {
      "id": "j_iMYLTy0KE",
      "title": "Tor Jonnyo",
      "artist": "Release",
      "duration_ms": 242000
    },
    {
      "id": "N4MsUDM2iYs",
      "title": "The Tower (Bonus Track)",
      "artist": "Ramin Djawadi",
      "duration_ms": 154000
    },
    {
      "id": "TSTo_D9ImS0",
      "title": "TRUCKS IN PLACE",
      "artist": "Ludwig Goransson",
      "duration_ms": 333000
    },
    {
      "id": "P0ohJJVZlwM",
      "title": "Truth",
      "artist": "Ramin Djawadi",
      "duration_ms": 212000
    },
    {
      "id": "P4NwOb39sTQ",
      "title": "Tu Hi Re (From \"Bombay\")",
      "artist": "Hariharan",
      "duration_ms": 436000
    },
    {
      "id": "3E1NLVzDZ_Y",
      "title": "Tujh Mein Rab Dikhta Hai",
      "artist": "Roopkumar Rathod (Official)",
      "duration_ms": 282000
    },
    {
      "id": "TEYraUzXSHc",
      "title": "Tujh Mein Rab Dikhta Hai - II",
      "artist": "Shreya Ghoshal Official",
      "duration_ms": 102000
    },
    {
      "id": "uTEOM40HGkg",
      "title": "Tujh Mein Rab Dikhta Hai - LoFi Mix",
      "artist": "The Folk \u0026 Soul Studio",
      "duration_ms": 195000
    },
    {
      "id": "mgl9dA4VeXs",
      "title": "Tum Hi Ho (From \"Aashiqui 2\")",
      "artist": "Arijit Singh",
      "duration_ms": 262000
    },
    {
      "id": "AqVIQ9ymvM8",
      "title": "Tum Ho",
      "artist": "Mohit Chauhan",
      "duration_ms": 317000
    },
    {
      "id": "YJWR_MVFigs",
      "title": "Tum Ko Dekha To Yeh Khayal Aaya",
      "artist": "Jagjit Singh",
      "duration_ms": 292000
    },
    {
      "id": "ftqkx5QEbM8",
      "title": "Tumi Ashbe Bole",
      "artist": "AMI E NACHIKETA",
      "duration_ms": 272000
    },
    {
      "id": "ddF-axdrB8w",
      "title": "Tumi Jake Bhalobaso (Male Version)",
      "artist": "Anupam Roy",
      "duration_ms": 296000
    },
    {
      "id": "O3wFQPpsvms",
      "title": "Tumi Robe Nirobe",
      "artist": "Release",
      "duration_ms": 167000
    },
    {
      "id": "8VKD-IlvibI",
      "title": "Unholy",
      "artist": "SAM SMITH",
      "duration_ms": 157000
    },
    {
      "id": "I90KY3HNm0Y",
      "title": "Unstoppable",
      "artist": "Sia",
      "duration_ms": 218000
    },
    {
      "id": "Ug1wLYiowvM",
      "title": "Ure Jaak",
      "artist": "Anupam Roy",
      "duration_ms": 269000
    },
    {
      "id": "Kdcg6NwczcM",
      "title": "Uthche Jege Shokalgulo",
      "artist": "Shreya Ghoshal Official",
      "duration_ms": 232000
    },
    {
      "id": "RCDItRwm8UU",
      "title": "Venom (Music From The Motion Picture)",
      "artist": "EminemMusic",
      "duration_ms": 270000
    },
    {
      "id": "pB-B6DUY0OY",
      "title": "Venom (Music From The Motion Picture)",
      "artist": "EminemMusic",
      "duration_ms": 270000
    },
    {
      "id": "v4dxDyCWglQ",
      "title": "Violin Concerto No. 2 in B Minor, Op. 7: III. Rondo \"La campanella\" (Arr. Kreisler for Violin...",
      "artist": "Camille et Julie Berthollet",
      "duration_ms": 318000
    },
    {
      "id": "Nv3eBblvRjU",
      "title": "Visit to Hida",
      "artist": "RADWIMPS",
      "duration_ms": 93000
    },
    {
      "id": "ALsvdSA9tOU",
      "title": "Viva La Vida",
      "artist": "Coldplay",
      "duration_ms": 243000
    },
    {
      "id": "ktF_D0-ndCE",
      "title": "Vivaldi Storm",
      "artist": "2CELLOS",
      "duration_ms": 154000
    },
    {
      "id": "ulRXvH8VOl8",
      "title": "Wake Me up When September Ends",
      "artist": "Green Day",
      "duration_ms": 286000
    },
    {
      "id": "sYwDeqoO7lo",
      "title": "Want You Gone",
      "artist": "Aperture Science Psychoacoustic Laboratories",
      "duration_ms": 144000
    },
    {
      "id": "RTRr7ApNhJ4",
      "title": "Warrior Of Light (From The \"Game Of Thrones: Season 2\" Soundtrack)",
      "artist": "Ramin Djawadi",
      "duration_ms": 185000
    },
    {
      "id": "mlsxPzkMTd4",
      "title": "Warriors",
      "artist": "ImagineDragons",
      "duration_ms": 173000
    },
    {
      "id": "KPM_BYl-EaQ",
      "title": "Watermelon Sugar",
      "artist": "Harry Styles",
      "duration_ms": 174000
    },
    {
      "id": "YTCS7IWUJu8",
      "title": "Way down We Go",
      "artist": "KALEO",
      "duration_ms": 214000
    },
    {
      "id": "S4O15lbUDj8",
      "title": "We Don't Talk Anymore (feat. Selena Gomez)",
      "artist": "Charlie Puth",
      "duration_ms": 218000
    },
    {
      "id": "-nPlo3wM-Zw",
      "title": "We Will Rock You (Remastered 2011)",
      "artist": "Queen Official",
      "duration_ms": 123000
    },
    {
      "id": "Ibaze-ZF3Vk",
      "title": "Welcome To Los Santos",
      "artist": "Oh No",
      "duration_ms": 155000
    },
    {
      "id": "DPe2diiGJRE",
      "title": "Wellerman (Sea Shanty)",
      "artist": "NathanEvanss",
      "duration_ms": 156000
    },
    {
      "id": "D458Eaql_aQ",
      "title": "Wellerman (Sea Shanty)",
      "artist": "NathanEvanss",
      "duration_ms": 157000
    },
    {
      "id": "Jrprk5dNboI",
      "title": "What I've Done",
      "artist": "Linkin Park",
      "duration_ms": 206000
    },
    {
      "id": "TePXIhCtNmE",
      "title": "What Is Dead May Never Die (From The \"Game Of Thrones: Season 2\" Soundtrack)",
      "artist": "Ramin Djawadi",
      "duration_ms": 128000
    },
    {
      "id": "cnRB2CgUpSw",
      "title": "Whatever It Takes",
      "artist": "ImagineDragons",
      "duration_ms": 202000
    },
    {
      "id": "6VG6gIvcjU8",
      "title": "Where Is My Mind? (2007 Remaster)",
      "artist": "PixiesOfficial",
      "duration_ms": 235000
    },
    {
      "id": "-jAtHf9RA4w",
      "title": "Whiplash",
      "artist": "Hank Levy",
      "duration_ms": 116000
    },
    {
      "id": "EMM-L74Xz8c",
      "title": "The Whirling Ways of Stars that Pass",
      "artist": "Jóhann Jóhannsson",
      "duration_ms": 113000
    },
    {
      "id": "JVTS3fyoAEQ",
      "title": "Who's Ready for Tomorrow",
      "artist": "RAT BOY",
      "duration_ms": 117000
    },
    {
      "id": "osTcYcYmf0o",
      "title": "A Window to the Past",
      "artist": "John Williams",
      "duration_ms": 235000
    },
    {
      "id": "8AofJHFt_lw",
      "title": "The Winds of Winter",
      "artist": "Ramin Djawadi",
      "duration_ms": 210000
    },
    {
      "id": "VmSxEEbVbjo",
      "title": "Winter Has Come",
      "artist": "Ramin Djawadi",
      "duration_ms": 195000
    },
    {
      "id": "bev2OqiMfYg",
      "title": "Winter Is Here",
      "artist": "Ramin Djawadi",
      "duration_ms": 175000
    },
    {
      "id": "eV60IJ46FY0",
      "title": "Winter Warmth",
      "artist": "Jordy Chandra",
      "duration_ms": 88000
    },
    {
      "id": "VfYigaMKrLw",
      "title": "Winterfell (From The \"Game Of Thrones: Season 2\" Soundtrack)",
      "artist": "Ramin Djawadi",
      "duration_ms": 164000
    },
    {
      "id": "tqxRidAWER8",
      "title": "Without Me",
      "artist": "EminemMusic",
      "duration_ms": 291000
    },
    {
      "id": "jpsUPdNthGY",
      "title": "Wolf Totem",
      "artist": "The HU",
      "duration_ms": 338000
    },
    {
      "id": "DaXGQ7JaOhQ",
      "title": "YAAD HAI NA",
      "artist": "Arijit Singh",
      "duration_ms": 247000
    },
    {
      "id": "SlIJs_yA1SQ",
      "title": "Ye Jawani Hai Diwani (From \"Jawani Diwani\")",
      "artist": "Kishore Kumar",
      "duration_ms": 267000
    },
    {
      "id": "G8wCaZ2Kok8",
      "title": "Halka Halka Saroor",
      "artist": "Nusrat Fateh Ali Khan",
      "duration_ms": 435000
    },
    {
      "id": "3TndEMf6zws",
      "title": "Ye Honsla",
      "artist": "Salim Sulaiman Music",
      "duration_ms": 288000
    },
    {
      "id": "7QDjInJ_nMM",
      "title": "Yeh Lal Rang Kab Mujhe Chhodega",
      "artist": "Kishore Kumar",
      "duration_ms": 244000
    },
    {
      "id": "BQJVOJUPJ30",
      "title": "Yeh Raaten Yeh Mausam",
      "artist": "Kishore Kumar",
      "duration_ms": 202000
    },
    {
      "id": "UQn_G22w8PA",
      "title": "Yeh Raaten Yeh Mausam",
      "artist": "Release",
      "duration_ms": 209000
    },
    {
      "id": "JNtZj3NaUFw",
      "title": "Yeh Sham Mastani",
      "artist": "Kishore Kumar",
      "duration_ms": 277000
    },
    {
      "id": "9qnqYL0eNNI",
      "title": "Yellow",
      "artist": "Coldplay",
      "duration_ms": 267000
    },
    {
      "id": "NrgmdOz227I",
      "title": "Yesterday (Remastered 2009)",
      "artist": "The Beatles",
      "duration_ms": 126000
    },
    {
      "id": "yd8IMTzc2bI",
      "title": "You Know Nothing",
      "artist": "Ramin Djawadi",
      "duration_ms": 200000
    },
    {
      "id": "m3DPp4txoy0",
      "title": "Yuve Yuve Yu",
      "artist": "The HU",
      "duration_ms": 283000
    },
    {
      "id": "V1_5SHc21m8",
      "title": "Zara Sa",
      "artist": "Pritam",
      "duration_ms": 304000
    },
    {
      "id": "3KnWkfPQz3Q",
      "title": "Zara Zara",
      "artist": "Bombay Jayashri Ramnath",
      "duration_ms": 299000
    },
    {
      "id": "t4J4-K-90Ok",
      "title": "Zaroori Tha",
      "artist": "The Folk \u0026 Soul Studio",
      "duration_ms": 343000
    },
    {
      "id": "qp0AktOIAag",
      "title": "Zenzenzense - movie ver.",
      "artist": "RADWIMPS",
      "duration_ms": 286000
    },
    {
      "id": "k7QNc9rrDhk",
      "title": "[What A] Wonderful World  (Mono)",
      "artist": "Sam Cooke",
      "duration_ms": 129000
    },
    {
      "id": "vTMAa6zZ7jY",
      "title": "7 Years",
      "artist": "Lukas Graham",
      "duration_ms": 238000
    },
    {
      "id": "RTwknWM68oE",
      "title": "295",
      "artist": "Sidhu Moose Wala",
      "duration_ms": 271000
    },
    {
      "id": "_uJDnBAikrQ",
      "title": "747",
      "artist": "Ludwig Goransson",
      "duration_ms": 425000
    },
    {
      "id": "IzKQBo1gLYg",
      "title": "这样很好 (Isha's Song) (from the series Arcane League of Legends)",
      "artist": "Eason Chan",
      "duration_ms": 265000
    },
    {
      "id": "QGNcfBhGFdc",
      "title": "Aadat (From \"Kalyug\")",
      "artist": "Atif Aslam",
      "duration_ms": 334000
    },
    {
      "id": "B0hrCwZoXW0",
      "title": "Aadmi Chutiya Hai",
      "artist": "Rahgir Live",
      "duration_ms": 227000
    },
    {
      "id": "PsJApYb7n-g",
      "title": "Aaha Tomar Shonge",
      "artist": "Sourendro-Soumyojit",
      "duration_ms": 244000
    },
    {
      "id": "JlGdhAuNyUc",
      "title": "AAOGE JAB TUM",
      "artist": "Rashid Kaithwadiya",
      "duration_ms": 356000
    },
    {
      "id": "r2yk5WkkOlk",
      "title": "Aap Ki Nazron Ne Samjha",
      "artist": "Lata Mangeshkar",
      "duration_ms": 235000
    },
    {
      "id": "p8eD8PQcC8I",
      "title": "Aasan Nahin Yahan",
      "artist": "Arijit Singh",
      "duration_ms": 215000
    },
    {
      "id": "icUNetVgCQQ",
      "title": "Aathma Raama",
      "artist": "Brodha V",
      "duration_ms": 235000
    },
    {
      "id": "3vqrhaP5Vxk",
      "title": "Jodi Abar Asi",
      "artist": "Rupankar",
      "duration_ms": 364000
    },
    {
      "id": "MtK2KF3YsLM",
      "title": "Abar Phire Ele (Original Motion Picture Soundtrack)",
      "artist": "Release",
      "duration_ms": 308000
    },
    {
      "id": "gwmx92MvFk4",
      "title": "Abhi Mujh Mein Kahin",
      "artist": "Ajay-Atul",
      "duration_ms": 365000
    },
    {
      "id": "0arf5Pasqjo",
      "title": "Achyutam Keshavam",
      "artist": "Saloni Thakkar",
      "duration_ms": 260000
    },
    {
      "id": "i5QCimZ8S4o",
      "title": "Across the Oceans of Time",
      "artist": "Ramin Djawadi",
      "duration_ms": 231000
    },
    {
      "id": "yn6H_9HLnnA",
      "title": "Act My Age",
      "artist": "One Direction",
      "duration_ms": 199000
    },
    {
      "id": "uH3Kv3fuU3I",
      "title": "Aadhkhana Aador",
      "artist": "Chandrabindoo",
      "duration_ms": 324000
    },
    {
      "id": "SMlGGRAB3Hc",
      "title": "Afreen Afreen",
      "artist": "The Folk \u0026 Soul Studio",
      "duration_ms": 401000
    },
    {
      "id": "gqljS57gkEE",
      "title": "Again from Your Lie in April",
      "artist": "Theishter",
      "duration_ms": 174000
    },
    {
      "id": "KD9gfThEjHA",
      "title": "Again to Goshintai",
      "artist": "RADWIMPS",
      "duration_ms": 144000
    },
    {
      "id": "dpBMlhldZqE",
      "title": "Against All Odds",
      "artist": "Ramin Djawadi",
      "duration_ms": 469000
    },
    {
      "id": "Wf3HSUv9AuU",
      "title": "Ogo Bideshini",
      "artist": "Anjan Dutt",
      "duration_ms": 238000
    },
    {
      "id": "8jjbhrR15Y8",
      "title": "Ain't No Sunshine",
      "artist": "Bill Withers",
      "duration_ms": 126000
    },
    {
      "id": "bdS6OoH1W2A",
      "title": "Ajab Si",
      "artist": "Vishal - Shekhar",
      "duration_ms": 242000
    },
    {
      "id": "jkcDydsPr0I",
      "title": "Aji Bijon Gharey Nishi Raate",
      "artist": "Hemanta Mukherjee  ",
      "duration_ms": 217000
    },
    {
      "id": "bir1X2KOy98",
      "title": "All Gone",
      "artist": "Gustavo Santaolalla",
      "duration_ms": 74000
    },
    {
      "id": "0MydzLWjx_8",
      "title": "All Gone (Alone)",
      "artist": "Gustavo Santaolalla",
      "duration_ms": 83000
    },
    {
      "id": "mP7fmRzzlj4",
      "title": "Alote Alote Dhaka",
      "artist": "Anupam Roy",
      "duration_ms": 313000
    },
    {
      "id": "ilgT99XFUq8",
      "title": "Amake Aamar Moto Thaakte Dao",
      "artist": "Anupam Roy",
      "duration_ms": 322000
    },
    {
      "id": "pLHheriMB_U",
      "title": "Amar Haat Bandhibi",
      "artist": "Sahana Bajpaie",
      "duration_ms": 300000
    },
    {
      "id": "_gagqT6_FpM",
      "title": "Amaro Parano",
      "artist": "Srikanto Acharya",
      "duration_ms": 481000
    },
    {
      "id": "LoVDfWC4ZTI",
      "title": "Amaro Porano",
      "artist": "Alokananda Dasgupta",
      "duration_ms": 126000
    },
    {
      "id": "paqnlixaD8A",
      "title": "Amaro Porano Jaha Chay",
      "artist": "Madhuraa Bhattacharya",
      "duration_ms": 279000
    },
    {
      "id": "p3PL73SeZC0",
      "title": "Ami Shunechi Sedin Tumi",
      "artist": "Provat Tonoy",
      "duration_ms": 275000
    },
    {
      "id": "yGsiGmItUn0",
      "title": "The Android Hell Blues (Extended)",
      "artist": "Harry101UK",
      "duration_ms": 269000
    },
    {
      "id": "aJBZvnbS9vM",
      "title": "Apur Paayer Chhaap (Original Motion Picture Soundtrack)",
      "artist": "Release",
      "duration_ms": 246000
    },
    {
      "id": "7RjRB35Gu0M",
      "title": "The Army of the Dead",
      "artist": "Ramin Djawadi",
      "duration_ms": 327000
    },
    {
      "id": "nujn6wbr-e8",
      "title": "As It Was",
      "artist": "Harry Styles",
      "duration_ms": 168000
    },
    {
      "id": "WM0waOKjzkE",
      "title": "Asatoma Sadgamaya",
      "artist": "Arijit Singh",
      "duration_ms": 187000
    },
    {
      "id": "vxUBYHz_q1I",
      "title": "Attention",
      "artist": "Charlie Puth",
      "duration_ms": 212000
    },
    {
      "id": "Tw8iApinXoU",
      "title": "Aur Ho",
      "artist": "Mohit Chauhan",
      "duration_ms": 333000
    },
    {
      "id": "9vWNauaZAgg",
      "title": "Back In Black",
      "artist": "AC/DC",
      "duration_ms": 256000
    },
    {
      "id": "jHkA2dsSl2g",
      "title": "Back in the 90's (From \"BoJack Horseman\")",
      "artist": "Alex Heflin",
      "duration_ms": 176000
    },
    {
      "id": "FBw-Z8ULwcc",
      "title": "Back in the 90's",
      "artist": "GROUPLOVE",
      "duration_ms": 44000
    },
    {
      "id": "eaiZ25dIDUk",
      "title": "Bade Achhe Lagte Hain",
      "artist": "Amit Kumar",
      "duration_ms": 313000
    },
    {
      "id": "Ja2BC0ZbO2w",
      "title": "Bahu Manaratha",
      "artist": "Release",
      "duration_ms": 194000
    },
    {
      "id": "Crz-7qYPPWM",
      "title": "Banbhashi",
      "artist": "Chandrabindoo",
      "duration_ms": 265000
    },
    {
      "id": "2JoneOW9HA4",
      "title": "Bandhu Chol",
      "artist": "Anupam Roy",
      "duration_ms": 453000
    },
    {
      "id": "SgJ_9aLfeds",
      "title": "Bandhu Tomaye",
      "artist": "Chandrabindoo",
      "duration_ms": 454000
    },
    {
      "id": "Nr5iUmlkzVI",
      "title": "Barso Re (From \"Guru\")",
      "artist": "A. R. Rahman",
      "duration_ms": 330000
    },
    {
      "id": "4XSyasr0w8k",
      "title": "Battle Symphony",
      "artist": "Linkin Park",
      "duration_ms": 217000
    },
    {
      "id": "ihufN7et2xQ",
      "title": "Bawshonto Eshe Geche (Female)",
      "artist": "Lagnajita Chakraborty",
      "duration_ms": 244000
    },
    {
      "id": "OyOVxiM-4jA",
      "title": "Bawshonto Eshe Geche (Male)",
      "artist": "Anupam Roy",
      "duration_ms": 252000
    },
    {
      "id": "ZWKpPDI1M-o",
      "title": "Beggin'",
      "artist": "Måneskin Official",
      "duration_ms": 212000
    },
    {
      "id": "nt0TNLlLxl8",
      "title": "Behaya (From Ekannoborti)",
      "artist": "Lagnajita Chakraborty",
      "duration_ms": 211000
    },
    {
      "id": "Kx7B-XvmFtE",
      "title": "Believer",
      "artist": "ImagineDragons",
      "duration_ms": 205000
    },
    {
      "id": "hO0TuYMIsGg",
      "title": "Berzerk",
      "artist": "EminemMusic",
      "duration_ms": 239000
    },
    {
      "id": "husKIjBIUdk",
      "title": "Bhalo Achi Bhalo Theko",
      "artist": "Adarsh Ray",
      "duration_ms": 272000
    },
    {
      "id": "td2UdfVkgXk",
      "title": "Bhalobashar Bhitte (From \"Belashuru\")",
      "artist": "Anindya Chatterjee",
      "duration_ms": 272000
    },
    {
      "id": "yIeFCSeE15M",
      "title": "Bhare Naina",
      "artist": "Nandini Srikar",
      "duration_ms": 361000
    },
    {
      "id": "ZiDtSKs6SSk",
      "title": "Bhindeshi Tara",
      "artist": "Chandrabindoo",
      "duration_ms": 277000
    },
    {
      "id": "sTZiSQ1PZ9g",
      "title": "Bhool Bhulaiyaa",
      "artist": "Neeraj Shridhar",
      "duration_ms": 326000
    },
    {
      "id": "H2PaSJvM3X0",
      "title": "Bhromor",
      "artist": "Surojit Chatterjee",
      "duration_ms": 196000
    },
    {
      "id": "0QXHXqhKfUA",
      "title": "Bhula Dena",
      "artist": "Mustafa Zahid",
      "duration_ms": 241000
    },
    {
      "id": "e5kFWasyufE",
      "title": "Bibagi Phone (From Dilkhush)",
      "artist": "Nilayan Chatterjee",
      "duration_ms": 226000
    },
    {
      "id": "iM3rXuqHxoQ",
      "title": "Bideshini",
      "artist": "Soumyadeep Sarkar",
      "duration_ms": 194000
    },
    {
      "id": "JCf7lKL1UQ4",
      "title": "Big Dawgs",
      "artist": "Hanumankind",
      "duration_ms": 191000
    },
    {
      "id": "Kr4EQDVETuA",
      "title": "Billie Jean",
      "artist": "Michael Jackson",
      "duration_ms": 295000
    },
    {
      "id": "Sa-dxgZt4rY",
      "title": "Birds",
      "artist": "ImagineDragons",
      "duration_ms": 220000
    },
    {
      "id": "J7p4bzqLvCw",
      "title": "Blinding Lights",
      "artist": "The Weeknd",
      "duration_ms": 202000
    },
    {
      "id": "MCC2CNS5lRQ",
      "title": "Blood of My Blood",
      "artist": "Ramin Djawadi",
      "duration_ms": 216000
    },
    {
      "id": "L3Olkm4jkM0",
      "title": "Blood of the Dragon",
      "artist": "Ramin Djawadi",
      "duration_ms": 94000
    },
    {
      "id": "ffe2EJfxg3o",
      "title": "BoJack's Theme",
      "artist": "Patrick Carney",
      "duration_ms": 57000
    },
    {
      "id": "UkhHY7U3LwU",
      "title": "BoJack's Theme (Full Length)",
      "artist": "Patrick Carney",
      "duration_ms": 264000
    },
    {
      "id": "igWPsrb_T4I",
      "title": "Bojhena Shey Bojhena",
      "artist": "Arijit Singh",
      "duration_ms": 430000
    },
    {
      "id": "gYuO6OUm6SQ",
      "title": "僕の戦争",
      "artist": "かまってチャンネル【公式】",
      "duration_ms": 281000
    },
    {
      "id": "V2SVRJ6dcE4",
      "title": "Bones",
      "artist": "ImagineDragons",
      "duration_ms": 166000
    },
    {
      "id": "gYCTXzOTnXg",
      "title": "Boulevard of Broken Dreams",
      "artist": "Green Day",
      "duration_ms": 263000
    },
    {
      "id": "ilfYnhXD-bE",
      "title": "Breaking Bad Main Title Theme (Extended)",
      "artist": "Dave Porter",
      "duration_ms": 76000
    },
    {
      "id": "_e7bqZGPyFI",
      "title": "Breaking the Habit",
      "artist": "Linkin Park",
      "duration_ms": 197000
    },
    {
      "id": "C_sz8xoZgbo",
      "title": "Breathless [album - Breathless '98]",
      "artist": "Shankar Mahadevan",
      "duration_ms": 183000
    },
    {
      "id": "70pa_nGM4Wo",
      "title": "Breathless",
      "artist": "Shankar Mahadevan",
      "duration_ms": 178000
    },
    {
      "id": "1Uh03H6R23g",
      "title": "Breathless Hanuman Chalisa",
      "artist": "Shankar Mahadevan",
      "duration_ms": 226000
    },
    {
      "id": "ECwh1u4_Des",
      "title": "The Bridge",
      "artist": "Arcane",
      "duration_ms": 103000
    },
    {
      "id": "zJ0KO4Kec3w",
      "title": "Bulleya (From \"Ae Dil Hai Mushkil\")",
      "artist": "Pritam",
      "duration_ms": 349000
    },
    {
      "id": "757uQSaOEO0",
      "title": "BURN IT DOWN",
      "artist": "Linkin Park",
      "duration_ms": 231000
    },
    {
      "id": "fxHjlCBHuzA",
      "title": "Bye Bye Bye",
      "artist": "*NSYNC",
      "duration_ms": 201000
    },
    {
      "id": "10YHsVc01IY",
      "title": "Call Me Call Me",
      "artist": "Steve Conte NYC",
      "duration_ms": 283000
    },
    {
      "id": "4JZ-o3iAJv4",
      "title": "Can You Hear The Music",
      "artist": "Ludwig Goransson",
      "duration_ms": 111000
    },
    {
      "id": "x3X8eBGYY6U",
      "title": "Can't Help Falling in Love",
      "artist": "Elvis Presley",
      "duration_ms": 183000
    },
    {
      "id": "zLxXqEZ5OoA",
      "title": "Can't Hold Us (feat. Ray Dalton)",
      "artist": "Macklemore",
      "duration_ms": 259000
    },
    {
      "id": "c5w68Z-oX30",
      "title": "Cara Mia Addio",
      "artist": "Aperture Science Psychoacoustic Laboratories",
      "duration_ms": 156000
    },
    {
      "id": "38CRu1rCaKg",
      "title": "Caravan",
      "artist": "John Wasson",
      "duration_ms": 555000
    },
    {
      "id": "cMhTQtEYS24",
      "title": "Carnival of Rust",
      "artist": "Poets of the Fall (Official)",
      "duration_ms": 263000
    },
    {
      "id": "JnPh45jFQq8",
      "title": "CASTLE OF GLASS",
      "artist": "Linkin Park",
      "duration_ms": 206000
    },
    {
      "id": "Rg6OGGp7PhY",
      "title": "CHAANDANIYA",
      "artist": "Mohan Kanan",
      "duration_ms": 248000
    },
    {
      "id": "m-0IoQu6O20",
      "title": "Chaap Tilak",
      "artist": "Release",
      "duration_ms": 533000
    },
    {
      "id": "Y943FiZ-Uqw",
      "title": "Chammak Challo",
      "artist": "Vishal - Shekhar",
      "duration_ms": 228000
    },
    {
      "id": "ZaURV4XxdPI",
      "title": "Chand Sifarish",
      "artist": "Singer Shaan",
      "duration_ms": 276000
    },
    {
      "id": "jnqzrHuyezQ",
      "title": "Channa Mereya (Unplugged)",
      "artist": "Pritam",
      "duration_ms": 166000
    },
    {
      "id": "sTe_hPK2RHY",
      "title": "Chaos Is a Ladder",
      "artist": "Ramin Djawadi",
      "duration_ms": 179000
    },
    {
      "id": "XGkS_o15ofc",
      "title": "The Children",
      "artist": "Ramin Djawadi",
      "duration_ms": 162000
    },
    {
      "id": "cPHmTWNA3JI",
      "title": "Chirosokha He",
      "artist": "Srikanto Acharya",
      "duration_ms": 266000
    },
    {
      "id": "zKFzKIa_pIM",
      "title": "Chlorine",
      "artist": "twenty one pilots",
      "duration_ms": 325000
    },
    {
      "id": "3a3EOvuF61I",
      "title": "Chol Dotong Pahar",
      "artist": "Sohan Ali",
      "duration_ms": 308000
    },
    {
      "id": "e3Rnsz7XWkk",
      "title": "ჩუბინა",
      "artist": "East Duo",
      "duration_ms": 91000
    },
    {
      "id": "1bNmBKy2C9w",
      "title": "Chunar",
      "artist": "Arijit Singh",
      "duration_ms": 269000
    },
    {
      "id": "hTRjNaGe5Ek",
      "title": "Chyapta Golap",
      "artist": "Anjan Dutt",
      "duration_ms": 284000
    },
    {
      "id": "xkqfm3muuhM",
      "title": "City Of Stars (From \"La La Land\" Soundtrack)",
      "artist": "Ryan Gosling",
      "duration_ms": 150000
    },
    {
      "id": "fQLAyvDNmUU",
      "title": "City Of Stars",
      "artist": "Ryan Gosling",
      "duration_ms": 112000
    },
    {
      "id": "WPEVYK6ijhw",
      "title": "City Of Stars (Humming)",
      "artist": "Justin Hurwitz",
      "duration_ms": 163000
    },
    {
      "id": "K0MHlZQMXS0",
      "title": "Claire de Lune",
      "artist": "London Philharmonic Orchestra",
      "duration_ms": 245000
    },
    {
      "id": "ujrM3VvXbq8",
      "title": "Coffee Houser Sei Addata Aaj Aar Nei",
      "artist": "Manna Dey",
      "duration_ms": 387000
    },
    {
      "id": "rsf_gTZG4cI",
      "title": "Come and Get Your Love",
      "artist": "Redbone",
      "duration_ms": 206000
    },
    {
      "id": "ZEMBDKMtHqM",
      "title": "Come As You Are",
      "artist": "Nirvana",
      "duration_ms": 219000
    },
    {
      "id": "7GlsxNI4LVI",
      "title": "Cornfield Chase",
      "artist": "Hans Zimmer",
      "duration_ms": 127000
    },
    {
      "id": "R-W2aYdv1Sc",
      "title": "Coronation",
      "artist": "Ramin Djawadi",
      "duration_ms": 107000
    },
    {
      "id": "_GWKkqNoyEA",
      "title": "Counting Stars",
      "artist": "OneRepublic",
      "duration_ms": 258000
    },
    {
      "id": "VYsr8v1jMHI",
      "title": "Creepin'",
      "artist": "Metro Boomin",
      "duration_ms": 222000
    },
    {
      "id": "EMhv6fbmjvE",
      "title": "Dance of Dragons",
      "artist": "Ramin Djawadi",
      "duration_ms": 189000
    },
    {
      "id": "NjEVP05Dvz4",
      "title": "Dastaan - E - Om Shanti Om",
      "artist": "Vishal - Shekhar",
      "duration_ms": 427000
    },
    {
      "id": "FtMhJH_rui4",
      "title": "Date",
      "artist": "RADWIMPS",
      "duration_ms": 246000
    },
    {
      "id": "UgkvcWx8oXw",
      "title": "Day One (Interstellar Theme)",
      "artist": "Hans Zimmer",
      "duration_ms": 200000
    },
    {
      "id": "vYbRpbBd5xk",
      "title": "Daylight",
      "artist": "David Kushner",
      "duration_ms": 213000
    },
    {
      "id": "A09qTw2tqKk",
      "title": "Dear Friend Across The River (The Bridge) (feat. Rachel Hardy)",
      "artist": "Samuel Kim Music",
      "duration_ms": 235000
    },
    {
      "id": "YgHHmVXPd9k",
      "title": "Death Note Metal Medley",
      "artist": "ToxicxEternity",
      "duration_ms": 362000
    },
    {
      "id": "16hm8wxR4SM",
      "title": "Deewani Mastani",
      "artist": "Shreya Ghoshal Official",
      "duration_ms": 340000
    },
    {
      "id": "MRmsIwAUan8",
      "title": "Dekha Hoye Jay",
      "artist": "Subhranil Nandy",
      "duration_ms": 186000
    },
    {
      "id": "6IBcLSKtaB4",
      "title": "Dekhechhi Rupshagore",
      "artist": "Mahtim Shakib",
      "duration_ms": 235000
    },
    {
      "id": "3aTLJs8ySa8",
      "title": "Dekhechi Rupsagore",
      "artist": "Aritra Banerjee",
      "duration_ms": 217000
    },
    {
      "id": "EQxUY162Qls",
      "title": "Despacito",
      "artist": "2CELLOS",
      "duration_ms": 148000
    },
    {
      "id": "Pswx6OQp1Ks",
      "title": "Destroyer Of Worlds",
      "artist": "Ludwig Goransson",
      "duration_ms": 175000
    },
    {
      "id": "SSoBDsuOyUc",
      "title": "Dil Se Re",
      "artist": "Release",
      "duration_ms": 406000
    },
    {
      "id": "_TJZaE0FkKs",
      "title": "DIL TO BACHCHA HAI",
      "artist": "The Folk \u0026 Soul Studio",
      "duration_ms": 337000
    },
    {
      "id": "Gplxsk25GtY",
      "title": "Dillagi",
      "artist": "The Folk \u0026 Soul Studio",
      "duration_ms": 300000
    },
    {
      "id": "EIBfJrR0q-k",
      "title": "Don't Come Home A-Drinkin' (With Lovin' On Your Mind)",
      "artist": "Loretta Lynn",
      "duration_ms": 127000
    },
    {
      "id": "sOcBCtPB7Xo",
      "title": "Dragonstone",
      "artist": "Ramin Djawadi",
      "duration_ms": 307000
    },
    {
      "id": "MtLHwqbE1eI",
      "title": "Dream lantern",
      "artist": "RADWIMPS",
      "duration_ms": 132000
    },
    {
      "id": "jDmUgjWLj-I",
      "title": "DUAA",
      "artist": "Vishal - Shekhar",
      "duration_ms": 261000
    },
    {
      "id": "iSQcqtKY1cA",
      "title": "Dust",
      "artist": "Hans Zimmer",
      "duration_ms": 342000
    },
    {
      "id": "9fNrJMkTWEE",
      "title": "Dust in the Wind",
      "artist": "KANSAS",
      "duration_ms": 207000
    },
    {
      "id": "GqANp-YzP-8",
      "title": "E Tumi Kemon Tumi",
      "artist": "Rupankar",
      "duration_ms": 324000
    },
    {
      "id": "oIri4kxEudg",
      "title": "Ei Mayabi Chander Raate (From \"Baba Baby O\")",
      "artist": "Chamok Hasan",
      "duration_ms": 203000
    },
    {
      "id": "XSgYMm08czU",
      "title": "Ei Srabon (Original Motion Picture Soundtrack)",
      "artist": "Rupam \u0026 Fossils",
      "duration_ms": 222000
    },
    {
      "id": "cVZtR-XVKVA",
      "title": "Ei To Ami Chai",
      "artist": "Shreya Ghoshal Official",
      "duration_ms": 167000
    },
    {
      "id": "CeVneAR-dEM",
      "title": "Ek Chatur Naar Karke Sringar",
      "artist": "Kishore Kumar",
      "duration_ms": 382000
    },
    {
      "id": "sz-wrI1Pg4k",
      "title": "Ek Pyar Ka Naghma Hai - Sad",
      "artist": "Lata Mangeshkar",
      "duration_ms": 361000
    },
    {
      "id": "9xHEpWWcNKA",
      "title": "Ek Pyar Ka Naghma Hai (Shor-'72) Compilation",
      "artist": "Jagjit Singh",
      "duration_ms": 292000
    },
    {
      "id": "7wVylDF6_Vs",
      "title": "Ek Pyar Ka Naghma Hai - Happy",
      "artist": "Lata Mangeshkar",
      "duration_ms": 366000
    },
    {
      "id": "l5Schfa_3Wk",
      "title": "Ekhon Onek Raat",
      "artist": "Anupam Roy",
      "duration_ms": 226000
    },
    {
      "id": "d3AEU_A4nzQ",
      "title": "Eki Labonye",
      "artist": "Iman Chakraborty ",
      "duration_ms": 246000
    },
    {
      "id": "DfvRa5Nyy04",
      "title": "Eki Labonye Purno Prane",
      "artist": "Lagnajita Chakraborty",
      "duration_ms": 226000
    },
    {
      "id": "683ZQtm76rI",
      "title": "Eki Labonye Purno Prano",
      "artist": "Lopamudra Mitra",
      "duration_ms": 323000
    },
    {
      "id": "L8Q5g483gD0",
      "title": "The End",
      "artist": "Justin Hurwitz",
      "duration_ms": 47000
    },
    {
      "id": "Kf5pXDhx5Vc",
      "title": "End of Beginning",
      "artist": "Djo Music",
      "duration_ms": 160000
    },
    {
      "id": "IOrbP1OqNsg",
      "title": "Enemy (from the series Arcane League of Legends)",
      "artist": "ImagineDragons",
      "duration_ms": 174000
    },
    {
      "id": "vxa8ShIm9yw",
      "title": "Enemy (From the series Arcane League of Legends)",
      "artist": "ImagineDragons",
      "duration_ms": 174000
    },
    {
      "id": "53jU1y9qE3M",
      "title": "Enna Sona",
      "artist": "A. R. Rahman",
      "duration_ms": 214000
    },
    {
      "id": "L16vTRw9mDQ",
      "title": "Epilogue",
      "artist": "Justin Hurwitz",
      "duration_ms": 460000
    },
    {
      "id": "6CiTFdPJMdg",
      "title": "Era Sukher Lagi",
      "artist": "Iman Chakraborty ",
      "duration_ms": 230000
    },
    {
      "id": "730pJFferN4",
      "title": "Escaped Crusader",
      "artist": "Michael Giacchino",
      "duration_ms": 165000
    },
    {
      "id": "_XwiIjOPNo0",
      "title": "Esho Hey (LoFi)",
      "artist": "Shreya Ghoshal Official",
      "duration_ms": 189000
    },
    {
      "id": "llK08ljfj7Y",
      "title": "Every Grain of Sand",
      "artist": "Bob Dylan",
      "duration_ms": 372000
    },
    {
      "id": "ppzoBclWpaA",
      "title": "Everybody's Gotta Learn Sometime",
      "artist": "Beck",
      "duration_ms": 355000
    },
    {
      "id": "a5oQLNa3Z5E",
      "title": "Evoking memories",
      "artist": "RADWIMPS",
      "duration_ms": 104000
    },
    {
      "id": "q22Nv2JDFZ4",
      "title": "Einaudi: Experience",
      "artist": "Ludovico Einaudi",
      "duration_ms": 313000
    },
    {
      "id": "K892qn3U524",
      "title": "Ezio's Family",
      "artist": "JesperKyd",
      "duration_ms": 238000
    },
    {
      "id": "xfWLSGhu7Xc",
      "title": "Fagun Haway Haway",
      "artist": "Borno Chakroborty",
      "duration_ms": 184000
    },
    {
      "id": "yOW7Eh81Gto",
      "title": "Faint",
      "artist": "Linkin Park",
      "duration_ms": 163000
    },
    {
      "id": "2mXNRsyTitA",
      "title": "Faint",
      "artist": "Linkin Park",
      "duration_ms": 163000
    },
    {
      "id": "m_vBi-Hg-BU",
      "title": "Far From Any Road (Main Title Theme from \"True Detective\")",
      "artist": "The Handsome Family",
      "duration_ms": 167000
    },
    {
      "id": "sJ9KjmcJAA0",
      "title": "Farewell",
      "artist": "Ramin Djawadi",
      "duration_ms": 332000
    },
    {
      "id": "Y7SLch0WxDU",
      "title": "Fazaa - Reprise",
      "artist": "Varsha Singh Dhanoa",
      "duration_ms": 178000
    },
    {
      "id": "fCjf-zm4vbo",
      "title": "Final Masquerade",
      "artist": "Linkin Park",
      "duration_ms": 218000
    },
    {
      "id": "VBG_nrUuUu0",
      "title": "First view of tokyo",
      "artist": "RADWIMPS",
      "duration_ms": 80000
    },
    {
      "id": "ZXSK2VgCjQo",
      "title": "Fletcher's Song In Club",
      "artist": "Justin Hurwitz",
      "duration_ms": 90000
    },
    {
      "id": "CMXxBI7VHEw",
      "title": "For Cersei",
      "artist": "Ramin Djawadi",
      "duration_ms": 264000
    },
    {
      "id": "ps_RXJ69iQA",
      "title": "Forrest Gump Suite",
      "artist": "Alan Silvestri",
      "duration_ms": 530000
    },
    {
      "id": "8Kvdfgh34xI",
      "title": "Für Elise",
      "artist": "Junior dos Santos Silva",
      "duration_ms": 173000
    },
    {
      "id": "TynR9dRZJjU",
      "title": "Für Elise (Dark Version)",
      "artist": "Toms Mucenieks",
      "duration_ms": 425000
    },
    {
      "id": "hXeKLYN8kHg",
      "title": "Gaand Mein Danda",
      "artist": "Bodhi Tree",
      "duration_ms": 297000
    },
    {
      "id": "Tn2AIjTAl-c",
      "title": "Gahana Kusuma",
      "artist": "Hariharan",
      "duration_ms": 339000
    },
    {
      "id": "DtCFsAYGNL8",
      "title": "Gahana Kusuma Kunja Majhe",
      "artist": "Sounak Chattopadhyay",
      "duration_ms": 436000
    },
    {
      "id": "9VgoADESpw0",
      "title": "Game Of Thrones",
      "artist": "Ramin Djawadi",
      "duration_ms": 79000
    },
    {
      "id": "XZ4ro0Lr1GQ",
      "title": "Game of Thrones Medley",
      "artist": "2CELLOS",
      "duration_ms": 305000
    },
    {
      "id": "-5qqrMu_AZc",
      "title": "Gangsta's Paradise",
      "artist": "Coolio",
      "duration_ms": 241000
    },
    {
      "id": "dSfc4xLo-Zc",
      "title": "Ghawrbaari",
      "artist": "Anupam Roy",
      "duration_ms": 287000
    },
    {
      "id": "4eRdshiNGa4",
      "title": "Ghoomar (From \"Padmaavat\")",
      "artist": "Shreya Ghoshal Official",
      "duration_ms": 283000
    },
    {
      "id": "OkNx2kt0vV0",
      "title": "Glimpse of Us",
      "artist": "Joji",
      "duration_ms": 234000
    },
    {
      "id": "6J0HaJ67FOM",
      "title": "Gobhire Jao (Female)",
      "artist": "Shreya Ghoshal Official",
      "duration_ms": 295000
    },
    {
      "id": "mJRHIVIqLWo",
      "title": "Gobhire Jao (Male)",
      "artist": "Anupam Roy",
      "duration_ms": 296000
    },
    {
      "id": "nbqMIBYJlvk",
      "title": "Godzilla",
      "artist": "EminemMusic",
      "duration_ms": 211000
    },
    {
      "id": "LPrFRMIDNQ8",
      "title": "Good Goodbye (feat. Pusha T and Stormzy)",
      "artist": "Linkin Park",
      "duration_ms": 212000
    },
    {
      "id": "Qpbk1yaskIw",
      "title": "Good Job - He Was a Beautiful Player",
      "artist": "Release",
      "duration_ms": 89000
    },
    {
      "id": "ZwAMFzYbgu8",
      "title": "Goodbye Brother",
      "artist": "Ramin Djawadi",
      "duration_ms": 188000
    },
    {
      "id": "TTHskdFvhtU",
      "title": "Goshintai",
      "artist": "RADWIMPS",
      "duration_ms": 208000
    },
    {
      "id": "UCpW9Tc3fso",
      "title": "Grave of the Fireflies Theme (From 'Grave of the Fireflies')",
      "artist": "Anime Kei",
      "duration_ms": 109000
    },
    {
      "id": "EL7e5XrzanA",
      "title": "Green Bird",
      "artist": "Yoko Kanno / 菅野よう子",
      "duration_ms": 115000
    },
    {
      "id": "5j5SQ8Oj4Kk",
      "title": "Halka Halka",
      "artist": "The Folk \u0026 Soul Studio",
      "duration_ms": 274000
    },
    {
      "id": "m-HxTP3AHTg",
      "title": "Hallelujah",
      "artist": "2CELLOS",
      "duration_ms": 218000
    },
    {
      "id": "faBTaY97fUE",
      "title": "Hamari Galiyan Hoke Aana (Sad)",
      "artist": "Meena Mishra",
      "duration_ms": 154000
    },
    {
      "id": "f0J4zM83n4w",
      "title": "Hariye Jawar Gaan",
      "artist": "Anupam Roy",
      "duration_ms": 230000
    },
    {
      "id": "UJxutXtHQFI",
      "title": "Hasi (Female Version)",
      "artist": "Ami Mishra",
      "duration_ms": 193000
    },
    {
      "id": "bYmxIqG5bJE",
      "title": "HEAD OVER HEELS (Sped Up Version)",
      "artist": "Gun Boi Kaz",
      "duration_ms": 183000
    },
    {
      "id": "ej7dg3zrxMs",
      "title": "Hear Me Roar",
      "artist": "Ramin Djawadi",
      "duration_ms": 137000
    },
    {
      "id": "XDjB9E3YtUE",
      "title": "Heat Waves",
      "artist": "Glass Animals",
      "duration_ms": 239000
    },
    {
      "id": "h0OK2oOG1no",
      "title": "Heavy Is the Crown",
      "artist": "Linkin Park",
      "duration_ms": 168000
    },
    {
      "id": "B-XivnZunVM",
      "title": "Heavy Is The Crown (Original Score) (from the series Arcane League of Legends)",
      "artist": "Mike Shinoda",
      "duration_ms": 102000
    },
    {
      "id": "0BuRn3-KdJ4",
      "title": "Hokage Funeral",
      "artist": "Lars Sørensen",
      "duration_ms": 224000
    },
    {
      "id": "q5rmKX7OabA",
      "title": "Hollow Purple (Toji vs Gojo Piano Theme) \"Jujutsu Kaisen Season 2\"",
      "artist": "PHAROZEN",
      "duration_ms": 206000
    },
    {
      "id": "4u7kNELI76A",
      "title": "Homage",
      "artist": "Mild High Club",
      "duration_ms": 178000
    },
    {
      "id": "vMENPd4Jro8",
      "title": "Home",
      "artist": "Ramin Djawadi",
      "duration_ms": 151000
    },
    {
      "id": "S3pteHVvV8Q",
      "title": "A Horse with No Name",
      "artist": "Patrick Carney",
      "duration_ms": 276000
    },
    {
      "id": "GAHlAcsLlJY",
      "title": "Hoshwalon Ko Khabar Kya",
      "artist": "Jagjit Singh",
      "duration_ms": 307000
    },
    {
      "id": "-Y1i2vvzv8Y",
      "title": "Hotel California (2013 Remaster)",
      "artist": "Eagles",
      "duration_ms": 392000
    },
    {
      "id": "sgF90jKULdU",
      "title": "House of Black and White",
      "artist": "Ramin Djawadi",
      "duration_ms": 309000
    },
    {
      "id": "YeujhjoodEU",
      "title": "Hug From Dad",
      "artist": "Justin Hurwitz",
      "duration_ms": 75000
    },
    {
      "id": "7UmMidoCer0",
      "title": "Hum Mar Jayenge",
      "artist": "Tulsi Kumar",
      "duration_ms": 307000
    },
    {
      "id": "mb_P6xtu1Ek",
      "title": "Human",
      "artist": "Rag'n'Bone Man",
      "duration_ms": 201000
    },
    {
      "id": "H3Kzh6RrnMc",
      "title": "Hymn for the Weekend",
      "artist": "Coldplay",
      "duration_ms": 259000
    },
    {
      "id": "XkzfLxUGVcE",
      "title": "I Ain't Worried",
      "artist": "OneRepublic",
      "duration_ms": 149000
    },
    {
      "id": "8j-Y11lmeIs",
      "title": "I Am Hers, She Is Mine (From The \"Game Of Thrones: Season 2\" Soundtrack)",
      "artist": "Ramin Djawadi",
      "duration_ms": 139000
    },
    {
      "id": "g7W7MisCKWk",
      "title": "I Can't Hear It Now (from the series Arcane League of Legends)",
      "artist": "Freya Ridings",
      "duration_ms": 162000
    },
    {
      "id": "Rbgw_rduQpM",
      "title": "I Really Want to Stay at Your House",
      "artist": "Rosa Walton",
      "duration_ms": 247000
    },
    {
      "id": "0T-BCIFeqq8",
      "title": "I WANNA BE YOUR SLAVE",
      "artist": "Måneskin Official",
      "duration_ms": 174000
    },
    {
      "id": "nyuo9-OjNNg",
      "title": "I Wanna Be Yours",
      "artist": "Official Arctic Monkeys",
      "duration_ms": 184000
    },
    {
      "id": "Y9bGqIjUaG4",
      "title": "I Want It That Way",
      "artist": "Backstreet Boys",
      "duration_ms": 214000
    },
    {
      "id": "yTyi4ZBLC_I",
      "title": "I'LL BE GONE",
      "artist": "Linkin Park",
      "duration_ms": 212000
    },
    {
      "id": "L4tetTHHPEQ",
      "title": "I'm Forrest... Forrest Gump",
      "artist": "Alan Silvestri",
      "duration_ms": 160000
    },
    {
      "id": "pOGOeCzaHN4",
      "title": "Imagine",
      "artist": "2CELLOS",
      "duration_ms": 180000
    },
    {
      "id": "RMJjWbdeTFs",
      "title": "In Dino (From \"Life In a Metro\")",
      "artist": "Pritam",
      "duration_ms": 398000
    },
    {
      "id": "BLZWkjBXfN8",
      "title": "In the End",
      "artist": "Linkin Park",
      "duration_ms": 217000
    },
    {
      "id": "urSy6oPp9Tk",
      "title": "Introduction and Rondo capriccioso in A Minor, Op. 28",
      "artist": "Dong-Suk Kang",
      "duration_ms": 546000
    },
    {
      "id": "opw2wXR6kVM",
      "title": "INVERSION",
      "artist": "Ludwig Goransson",
      "duration_ms": 213000
    },
    {
      "id": "ZTmMxG-tI-U",
      "title": "Iridescent",
      "artist": "Linkin Park",
      "duration_ms": 297000
    },
    {
      "id": "Dy_eP-mqWow",
      "title": "Iris",
      "artist": "Goo Goo Dolls",
      "duration_ms": 290000
    },
    {
      "id": "ECVHWlAeJ9c",
      "title": "The Iron Throne",
      "artist": "Ramin Djawadi",
      "duration_ms": 340000
    },
    {
      "id": "-qsXaVlp0eI",
      "title": "Isq Risk",
      "artist": "The Folk \u0026 Soul Studio",
      "duration_ms": 295000
    },
    {
      "id": "yxvSVPeBPfM",
      "title": "Itomori high school",
      "artist": "RADWIMPS",
      "duration_ms": 112000
    },
    {
      "id": "uVqdzTMnn6s",
      "title": "JAANI DEKHA HOBE (MALE)",
      "artist": "Anupam Roy",
      "duration_ms": 367000
    },
    {
      "id": "leQFuTkxVns",
      "title": "Jag Soona Soona Lage",
      "artist": "Vishal - Shekhar",
      "duration_ms": 330000
    },
    {
      "id": "6MoZcTcERB8",
      "title": "Jane Woh Kaise Log The",
      "artist": "Hemanta Mukherjee  ",
      "duration_ms": 260000
    },
    {
      "id": "cr4Tz4JEP40",
      "title": "Jashn-E-Bahaaraa",
      "artist": "A. R. Rahman",
      "duration_ms": 316000
    },
    {
      "id": "0aPd0xWGpO8",
      "title": "Jatismar",
      "artist": "Kabir Suman",
      "duration_ms": 277000
    },
    {
      "id": "PNacQbYrH_E",
      "title": "Javeda Zindagi",
      "artist": "Kshitij Tarey",
      "duration_ms": 503000
    },
    {
      "id": "P0sMRDB-o3w",
      "title": "Jawkhon Porbena Mor",
      "artist": "Rupankar Bagchi",
      "duration_ms": 464000
    },
    {
      "id": "rXAcoP6-bcw",
      "title": "Je Kawta Din (Duet)",
      "artist": "Shreya Ghoshal Official",
      "duration_ms": 246000
    },
    {
      "id": "rvVQHi4d93Q",
      "title": "Je Kawta Din (Original Motion Picture Soundtrack)",
      "artist": "Anupam Roy",
      "duration_ms": 327000
    },
    {
      "id": "v0U3XePR8ls",
      "title": "Jenny of Oldstones",
      "artist": "Ramin Djawadi",
      "duration_ms": 151000
    },
    {
      "id": "2-F7K6UZEVg",
      "title": "Jenny of Oldstones (Game of Thrones)",
      "artist": "florencemachine",
      "duration_ms": 189000
    },
    {
      "id": "w3iDupANgDA",
      "title": "Jhalla Wallah",
      "artist": "Shreya Ghoshal Official",
      "duration_ms": 352000
    },
    {
      "id": "Jigu5xgCZ0Y",
      "title": "Jodi Bolo Hya",
      "artist": "Chandrabindoo",
      "duration_ms": 353000
    },
    {
      "id": "4x7GJZMx5KE",
      "title": "Jokhon Porbe Na More",
      "artist": "Srikanto Acharya",
      "duration_ms": 337000
    },
    {
      "id": "5s4fqJpXRvI",
      "title": "Kabhi Jo Baadal Barse (From \"Jackpot)",
      "artist": "Arijit Singh",
      "duration_ms": 255000
    },
    {
      "id": "r9eGi0rVxBw",
      "title": "KABHI KABHI ADITI",
      "artist": "Rashid Ali Warbartan",
      "duration_ms": 219000
    },
    {
      "id": "gmoucRvDfIk",
      "title": "KABIRA",
      "artist": "Tochi Raina",
      "duration_ms": 224000
    },
    {
      "id": "if7X8G9c3t0",
      "title": "Kalank (Title Track)",
      "artist": "Pritam",
      "duration_ms": 312000
    },
    {
      "id": "th8GjhuMnds",
      "title": "Karz Theme Music",
      "artist": "not applicable",
      "duration_ms": 194000
    },
    {
      "id": "mhpRipG9Zss",
      "title": "Katawaredoki",
      "artist": "RADWIMPS",
      "duration_ms": 171000
    },
    {
      "id": "3XU3mFXMuZU",
      "title": "Kehna Hi Kya (From \"Bombay\")",
      "artist": "K S Chithra",
      "duration_ms": 354000
    },
    {
      "id": "LirE0g-ysOs",
      "title": "Khachar Bhetor Ochin Pakhi",
      "artist": "SHUNNO",
      "duration_ms": 354000
    },
    {
      "id": "1qfWy7D5XTQ",
      "title": "Khachar Bhitor Achin Pakhi",
      "artist": "Satyaki Banerjee",
      "duration_ms": 364000
    },
    {
      "id": "lDxSYGczfSw",
      "title": "Khaleesi",
      "artist": "Ramin Djawadi",
      "duration_ms": 186000
    },
    {
      "id": "V6gay5BHQ3E",
      "title": "Kholo Kholo",
      "artist": "Raman Mahadevan",
      "duration_ms": 312000
    },
    {
      "id": "6rbF26tdqNU",
      "title": "Kichchu Chaini Aami (Female)",
      "artist": "Release",
      "duration_ms": 381000
    },
    {
      "id": "LBY0KVTX430",
      "title": "Kichhu Kichhu Kotha",
      "artist": "Arijit Singh",
      "duration_ms": 272000
    },
    {
      "id": "t4U66h3robc",
      "title": "King Of The North",
      "artist": "Ramin Djawadi",
      "duration_ms": 89000
    },
    {
      "id": "PwsUAxu6rjg",
      "title": "The King's Arrival",
      "artist": "Ramin Djawadi",
      "duration_ms": 214000
    },
    {
      "id": "5f5VC1UVuGA",
      "title": "Kiska Rasta Dekhe (From \"Joshila\")",
      "artist": "Kishore Kumar",
      "duration_ms": 257000
    },
    {
      "id": "0aKOApRJygg",
      "title": "A Knight of the Seven Kingdoms",
      "artist": "Ramin Djawadi",
      "duration_ms": 120000
    },
    {
      "id": "yILGpHb-OYE",
      "title": "Kolkata",
      "artist": "Anupam Roy",
      "duration_ms": 282000
    },
    {
      "id": "49nmQdgo-rc",
      "title": "Kon Gopone",
      "artist": "Release",
      "duration_ms": 179000
    },
    {
      "id": "_fmA1RoHbzA",
      "title": "Kun Faya Kun",
      "artist": "A. R. Rahman",
      "duration_ms": 471000
    },
    {
      "id": "pnO3eoy4j6U",
      "title": "Kun Faya Kun",
      "artist": "A. R. Rahman",
      "duration_ms": 471000
    },
    {
      "id": "y7fN6YNFnJ4",
      "title": "La Vie En Rose",
      "artist": "Emily Watts",
      "duration_ms": 158000
    },
    {
      "id": "gI7hyn18Xn8",
      "title": "Lag Ja Gale Se Phir",
      "artist": "Lata Mangeshkar",
      "duration_ms": 258000
    },
    {
      "id": "5qNtmne62Vo",
      "title": "A Lannister Always Pays His Debts",
      "artist": "Ramin Djawadi",
      "duration_ms": 171000
    },
    {
      "id": "VZILZ1rT1Sk",
      "title": "The Last of the Starks",
      "artist": "Ramin Djawadi",
      "duration_ms": 293000
    },
    {
      "id": "dQEiulaq4rk",
      "title": "The Last of Us",
      "artist": "Gustavo Santaolalla",
      "duration_ms": 68000
    },
    {
      "id": "Y2UOwvUQ8L0",
      "title": "The Last of Us",
      "artist": "Gustavo Santaolalla",
      "duration_ms": 184000
    },
    {
      "id": "-FDMVFzaIJ4",
      "title": "The Last of Us (A New Dawn)",
      "artist": "Gustavo Santaolalla",
      "duration_ms": 149000
    },
    {
      "id": "bhhSRkQzbwU",
      "title": "The Last of Us (Goodnight)",
      "artist": "Gustavo Santaolalla",
      "duration_ms": 51000
    },
    {
      "id": "Svpz2KMpmnE",
      "title": "The Last of Us (Never Again)",
      "artist": "Gustavo Santaolalla",
      "duration_ms": 62000
    },
    {
      "id": "s2NdE3axvfI",
      "title": "The Last of Us (You and Me)",
      "artist": "Gustavo Santaolalla",
      "duration_ms": 129000
    },
    {
      "id": "K5goifH_-vg",
      "title": "Leave Out All The Rest",
      "artist": "Linkin Park",
      "duration_ms": 210000
    },
    {
      "id": "R4hDcd9fzRk",
      "title": "Legends Never Die",
      "artist": "League of Legends",
      "duration_ms": 235000
    },
    {
      "id": "4ig41FsiuZI",
      "title": "Lemon Tree",
      "artist": "Fools Garden",
      "duration_ms": 192000
    },
    {
      "id": "Kcj5-jWxgKs",
      "title": "Let Me Down Slowly",
      "artist": "Alec Benjamin",
      "duration_ms": 170000
    },
    {
      "id": "rJ0D1GbDq1Q",
      "title": "Let Me Love You",
      "artist": "DJ Snake",
      "duration_ms": 206000
    },
    {
      "id": "6LASz6HAL7E",
      "title": "Light of the Seven",
      "artist": "Ramin Djawadi",
      "duration_ms": 590000
    },
    {
      "id": "8h53H094Pg8",
      "title": "Like a Brother",
      "artist": "Zolik",
      "duration_ms": 95000
    },
    {
      "id": "eAXSrnHDlfQ",
      "title": "Likhe Jo Khat Tujhe",
      "artist": "Mohammed Rafi",
      "duration_ms": 274000
    },
    {
      "id": "C2Uconj2F1g",
      "title": "Lily",
      "artist": "Alan Walker",
      "duration_ms": 196000
    },
    {
      "id": "cOfFWiVMUXs",
      "title": "The Line (from the series Arcane League of Legends)",
      "artist": "twenty one pilots",
      "duration_ms": 192000
    },
    {
      "id": "HMSxhsIlyhE",
      "title": "Lit (From \"Koe no Katachi\")",
      "artist": "Fonzi M - Melodies on Piano",
      "duration_ms": 265000
    },
    {
      "id": "WlA99PPNTik",
      "title": "Lose You To Love Me",
      "artist": "Selena Gomez",
      "duration_ms": 207000
    },
    {
      "id": "ZjB-sz62tJ8",
      "title": "Lose Yourself",
      "artist": "EminemMusic",
      "duration_ms": 327000
    },
    {
      "id": "Wj7lL6eDOqc",
      "title": "Lose Yourself (From \"8 Mile\" Soundtrack)",
      "artist": "EminemMusic",
      "duration_ms": 322000
    },
    {
      "id": "runQJVBO1GE",
      "title": "LOST IN THE ECHO",
      "artist": "Linkin Park",
      "duration_ms": 206000
    },
    {
      "id": "RnkShwdXfyc",
      "title": "Love The Way You Lie",
      "artist": "EminemMusic",
      "duration_ms": 264000
    },
    {
      "id": "RGIs8WQYIl0",
      "title": "Love The Way You Lie (Part II) (Pt. 2)",
      "artist": "Rihanna",
      "duration_ms": 297000
    },
    {
      "id": "Flb01Ni3p3M",
      "title": "Love Theme From \"The Godfather\"",
      "artist": "Nino Rota",
      "duration_ms": 159000
    },
    {
      "id": "MMfpp0-lnw4",
      "title": "lovely",
      "artist": "Billie Eilish",
      "duration_ms": 201000
    },
    {
      "id": "iqizXvvWnmM",
      "title": "Lumière",
      "artist": "Lorien Testard",
      "duration_ms": 222000
    },
    {
      "id": "AGgfFGrN88s",
      "title": "Ma Meilleure Ennemie (from the series Arcane League of Legends)",
      "artist": "Stromae",
      "duration_ms": 148000
    },
    {
      "id": "_8in7o0uItQ",
      "title": "Maati Khunre (Original Motion Picture Soundtrack)",
      "artist": "Anupam Roy",
      "duration_ms": 348000
    },
    {
      "id": "IBfiEL3E1VY",
      "title": "Madhubala",
      "artist": "Amit Trivedi",
      "duration_ms": 244000
    },
    {
      "id": "tXmPTtqcVKE",
      "title": "Maharajo (LoFi)",
      "artist": "Release",
      "duration_ms": 189000
    },
    {
      "id": "fXoPjmXShZI",
      "title": "Main Agar Kahoon",
      "artist": "Sonu Nigam",
      "duration_ms": 309000
    },
    {
      "id": "Ov5ljc44Ajs",
      "title": "Main Title",
      "artist": "Ramin Djawadi",
      "duration_ms": 107000
    },
    {
      "id": "yZU_PJx8FX4",
      "title": "Main Title (from “Game of Thrones”)",
      "artist": "Ramin Djawadi",
      "duration_ms": 106000
    },
    {
      "id": "-gYzHEDm8e4",
      "title": "Majhe Majhe Tabo Dekha Pai",
      "artist": "Arnob",
      "duration_ms": 364000
    },
    {
      "id": "9SBhvTqlfKk",
      "title": "Malang - Extended Version",
      "artist": "Siddharth Mahadevan",
      "duration_ms": 362000
    },
    {
      "id": "o0WWaA3oFa4",
      "title": "A Man Without Love",
      "artist": "Engelbert Humperdinck",
      "duration_ms": 204000
    },
    {
      "id": "85RUn6tql7k",
      "title": "Manja (From \"Kai Po Che\")",
      "artist": "Amit Trivedi",
      "duration_ms": 217000
    },
    {
      "id": "U8F2ZrxvulM",
      "title": "Mathura Nagarpati (Original Motion Picture Soundtrack)",
      "artist": "Shubha Mudgal",
      "duration_ms": 388000
    },
    {
      "id": "gBWSRhrgNm4",
      "title": "Maula Mere Lele Meri Jaan",
      "artist": "Release",
      "duration_ms": 288000
    },
    {
      "id": "ZfWSOs5YbQ8",
      "title": "Me and the Devil",
      "artist": "Soap\u0026Skin",
      "duration_ms": 185000
    },
    {
      "id": "Yd3vCQmk3pY",
      "title": "Meet",
      "artist": "Arijit Singh",
      "duration_ms": 216000
    },
    {
      "id": "P6Vlr2AeX60",
      "title": "Megh Bolechhe",
      "artist": "Arnob",
      "duration_ms": 208000
    },
    {
      "id": "lNilb-EaTOU",
      "title": "Memories",
      "artist": "Maroon 5",
      "duration_ms": 190000
    },
    {
      "id": "n_ABgnlFIcI",
      "title": "Mere Dholna",
      "artist": "Shreya Ghoshal Official",
      "duration_ms": 405000
    },
    {
      "id": "5HBy8glAEHE",
      "title": "Mere Dholna (Arijit Version)",
      "artist": "Arijit Singh",
      "duration_ms": 365000
    },
    {
      "id": "HbE2kVeN2JI",
      "title": "Mere Lala Aaj",
      "artist": "Release",
      "duration_ms": 277000
    },
    {
      "id": "odrhc32fiLo",
      "title": "Mere Mehboob Qayamat Hogi",
      "artist": "Kishore Kumar",
      "duration_ms": 229000
    },
    {
      "id": "6RchbVJpJRI",
      "title": "Mere Samnewali Khidki Mein",
      "artist": "Kishore Kumar",
      "duration_ms": 173000
    },
    {
      "id": "Des4vM1U7MA",
      "title": "Meri Aashiqui",
      "artist": "Palak Muchhal",
      "duration_ms": 267000
    },
    {
      "id": "hLydgs1Ummk",
      "title": "Message from Home",
      "artist": "Hans Zimmer",
      "duration_ms": 101000
    },
    {
      "id": "ggS5zjraJi4",
      "title": "Mhysa",
      "artist": "Ramin Djawadi",
      "duration_ms": 235000
    },
    {
      "id": "D3ovuBdbUqk",
      "title": "Mia \u0026 Sebastian’s Theme",
      "artist": "Justin Hurwitz",
      "duration_ms": 99000
    },
    {
      "id": "4zsVKROnQfY",
      "title": "MIDDLE OF THE NIGHT",
      "artist": "Elley Duhé",
      "duration_ms": 185000
    },
    {
      "id": "WgTEu6y9VbY",
      "title": "Mockingbird",
      "artist": "EminemMusic",
      "duration_ms": 252000
    },
    {
      "id": "Esa1Is5uFqQ",
      "title": "Mon Bhalo Nei (From \"Shaheb Bibi Golaam\")",
      "artist": "Anupam Roy",
      "duration_ms": 301000
    },
    {
      "id": "Oj2fDgOK278",
      "title": "Mon Kyamoner Jonmodin",
      "artist": "Mekhla Dasgupta",
      "duration_ms": 244000
    },
    {
      "id": "x1yvlgAhzQw",
      "title": "Mon Re Krishikaj Janona (Duet)",
      "artist": "Ramprasad Sen",
      "duration_ms": 293000
    },
    {
      "id": "3DZURGLGpXU",
      "title": "Moner Manush",
      "artist": "Anupam Roy",
      "duration_ms": 516000
    },
    {
      "id": "e4UKtfiX_wM",
      "title": "Monsters (feat. blackbear)",
      "artist": "All Time Low",
      "duration_ms": 175000
    },
    {
      "id": "ZikBTLDBmm4",
      "title": "MONTA RE",
      "artist": "Swanand Kirkire",
      "duration_ms": 238000
    },
    {
      "id": "9v4iyCbf2lE",
      "title": "Moonlight Sonata - 2nd Movement (Beethoven)",
      "artist": "Rousseau",
      "duration_ms": 202000
    },
    {
      "id": "PgdIZdUusoA",
      "title": "Mora Rasan",
      "artist": "Krameri Official",
      "duration_ms": 250000
    },
    {
      "id": "N-Du0r0WoVg",
      "title": "Mother of Dragons (From \"Game of Thrones\")",
      "artist": "The City of Prague Philharmonic Orchestra",
      "duration_ms": 148000
    },
    {
      "id": "TEoNlV4G_KQ",
      "title": "Mother Death (From \"Grave of the Fireflies\") - Piano Version",
      "artist": "Nikolai Tal",
      "duration_ms": 117000
    },
    {
      "id": "arNkB9vxS3Q",
      "title": "Mountains",
      "artist": "Hans Zimmer",
      "duration_ms": 220000
    },
    {
      "id": "pvfzcGbOzqg",
      "title": "Mr Blue",
      "artist": "Catherine Feeny",
      "duration_ms": 155000
    },
    {
      "id": "q8189_L8Kws",
      "title": "Mr. Forgettable",
      "artist": "David Kushner",
      "duration_ms": 188000
    },
    {
      "id": "5uNV5eRCcfg",
      "title": "My Heart Will Go On (from \"Titanic\")",
      "artist": "2CELLOS",
      "duration_ms": 344000
    },
    {
      "id": "Siz-xBfIqpg",
      "title": "My Heart Will Go On (Love Theme from \"Titanic\")",
      "artist": "Celine Dion",
      "duration_ms": 280000
    },
    {
      "id": "f04dd09akoo",
      "title": "My Lie",
      "artist": "Zolik",
      "duration_ms": 177000
    },
    {
      "id": "waHJsPu_fmU",
      "title": "Nadaan Parinde",
      "artist": "A. R. Rahman",
      "duration_ms": 384000
    },
    {
      "id": "n89SKAymNfA",
      "title": "Nandemonaiya - movie ver.",
      "artist": "RADWIMPS",
      "duration_ms": 345000
    },
    {
      "id": "xAj3Ru5sOBI",
      "title": "Nandemonaiya - movie edit.",
      "artist": "RADWIMPS",
      "duration_ms": 197000
    },
    {
      "id": "-lP4QbkP3Tc",
      "title": "Nayan Tomare",
      "artist": "Arnob",
      "duration_ms": 612000
    },
    {
      "id": "W2XCXFWpI0s",
      "title": "Needle",
      "artist": "Ramin Djawadi",
      "duration_ms": 177000
    },
    {
      "id": "iwbQrmmEiM0",
      "title": "Neel",
      "artist": "Chandrabindoo",
      "duration_ms": 309000
    },
    {
      "id": "fHW43Iu2c3c",
      "title": "New Divide",
      "artist": "Linkin Park",
      "duration_ms": 269000
    },
    {
      "id": "nL2HPPHdPAA",
      "title": "The Next Episode",
      "artist": "Dr. Dre",
      "duration_ms": 162000
    },
    {
      "id": "8BiLurrzFRw",
      "title": "Night Changes",
      "artist": "One Direction",
      "duration_ms": 227000
    },
    {
      "id": "ef-Nb3nw9hg",
      "title": "The Night King",
      "artist": "Ramin Djawadi",
      "duration_ms": 531000
    },
    {
      "id": "90DKXLbzLto",
      "title": "The Night We Met",
      "artist": "Lord Huron",
      "duration_ms": 209000
    },
    {
      "id": "H-iPavAXQUk",
      "title": "Nightcall",
      "artist": "KAVINSKY",
      "duration_ms": 259000
    },
    {
      "id": "2o9KfyPqQzY",
      "title": "No Time for Caution",
      "artist": "Hans Zimmer",
      "duration_ms": 247000
    },
    {
      "id": "XVvqLZNA_8s",
      "title": "No Two Words",
      "artist": "Justin Hurwitz",
      "duration_ms": 102000
    },
    {
      "id": "2pBZQ927u40",
      "title": "Noor E Khuda",
      "artist": "Shankar Ehsaan Loy",
      "duration_ms": 398000
    },
    {
      "id": "-grPV-Fae6I",
      "title": "Not Afraid",
      "artist": "EminemMusic",
      "duration_ms": 249000
    },
    {
      "id": "phLb_SoPBlA",
      "title": "Not Like Us",
      "artist": "Kendrick Lamar",
      "duration_ms": 275000
    },
    {
      "id": "Gth2OvAPNqM",
      "title": "Shaajo Shaajao Male (From \"Ballabhpurer Roopkotha')",
      "artist": "Anirban Bhattacharya",
      "duration_ms": 273000
    },
    {
      "id": "5qZQEq_C3vc",
      "title": "Numb",
      "artist": "Linkin Park",
      "duration_ms": 188000
    },
    {
      "id": "iphTneTGXBQ",
      "title": "O Bedardeya",
      "artist": "Arijit Singh",
      "duration_ms": 314000
    },
    {
      "id": "RVriPctnBls",
      "title": "O Je Mane Na Mana",
      "artist": "Release",
      "duration_ms": 153000
    },
    {
      "id": "MLws81EqS3M",
      "title": "O Je Mane Na Mana",
      "artist": "Sahana Bajpaie",
      "duration_ms": 262000
    },
    {
      "id": "NwWUcMU3iek",
      "title": "O Mere Dil Ke Chain",
      "artist": "Kishore Kumar",
      "duration_ms": 296000
    },
    {
      "id": "kMp-VM6BEoo",
      "title": "O Rangrez",
      "artist": "Release",
      "duration_ms": 385000
    },
    {
      "id": "n0XrpYxE34A",
      "title": "Obhabe Keno",
      "artist": "Anupam Roy",
      "duration_ms": 214000
    },
    {
      "id": "koJ1JjAw_jc",
      "title": "Oboseshe",
      "artist": "Arijit Singh",
      "duration_ms": 216000
    },
    {
      "id": "PXrY9ohnAVM",
      "title": "OFFO",
      "artist": "Aditi Singh Sharma",
      "duration_ms": 215000
    },
    {
      "id": "Of7J7QLqmho",
      "title": "One More Light",
      "artist": "Linkin Park",
      "duration_ms": 256000
    },
    {
      "id": "wsKw_Astidg",
      "title": "Otonoke",
      "artist": "Creepy Nuts",
      "duration_ms": 186000
    },
    {
      "id": "LdV2QjceLsw",
      "title": "Out of Time Man",
      "artist": "Mick Harvey",
      "duration_ms": 178000
    },
    {
      "id": "mOcXwT4JRrs",
      "title": "P.I.M.P. (Snoop Dogg Remix)",
      "artist": "50 Cent",
      "duration_ms": 289000
    },
    {
      "id": "cmEIneYW2yk",
      "title": "Paint The Town Blue (from the series Arcane League of Legends)",
      "artist": "Ashnikko",
      "duration_ms": 115000
    },
    {
      "id": "RJvynLX2ZKE",
      "title": "Pasoori (Shae Gill, Ali Sethi)",
      "artist": "Karolina Protsenko",
      "duration_ms": 15000
    },
    {
      "id": "swcCuuQKGJ4",
      "title": "Pehli Nazar Mein",
      "artist": "Pritam",
      "duration_ms": 313000
    },
    {
      "id": "ORrFJ63nlcA",
      "title": "Perfect",
      "artist": "Ed Sheeran",
      "duration_ms": 264000
    },
    {
      "id": "ili8S0-xDF0",
      "title": "Perfect",
      "artist": "2CELLOS",
      "duration_ms": 225000
    },
    {
      "id": "XT_ANSoov00",
      "title": "Phir Le Aya Dil (Reprise)",
      "artist": "Pritam",
      "duration_ms": 306000
    },
    {
      "id": "ga6Xy42d_go",
      "title": "Moonlight Sonata - 1st Movement (Beethoven)",
      "artist": "Rousseau",
      "duration_ms": 445000
    },
    {
      "id": "u30LsgDAcKs",
      "title": "Moonlight Sonata - 3rd Movement (Beethoven)",
      "artist": "Rousseau",
      "duration_ms": 455000
    },
    {
      "id": "-MeC5dLat-A",
      "title": "Pirates of the Caribbean",
      "artist": "2CELLOS",
      "duration_ms": 181000
    },
    {
      "id": "M2CZaOwOeQo",
      "title": "Piya Aaye Na",
      "artist": "Tulsi Kumar",
      "duration_ms": 287000
    },
    {
      "id": "zgJPTTiCK2E",
      "title": "Piya Ghar Aavenge",
      "artist": "Kailash Kher",
      "duration_ms": 343000
    },
    {
      "id": "bqVcc9hFXW4",
      "title": "Piya Tora Kaisa Abhiman (Male)",
      "artist": "Hariharan",
      "duration_ms": 339000
    },
    {
      "id": "rvnyVvSRAxs",
      "title": "Piyu Bole",
      "artist": "Sonu Nigam",
      "duration_ms": 266000
    },
    {
      "id": "MQCTWx9fSzc",
      "title": "The Plan (From the Motion Picture \"TENET\")",
      "artist": "Travis Scott",
      "duration_ms": 186000
    },
    {
      "id": "n3ce-9MdVKM",
      "title": "Chopin: Polonaise No. 6 in A-Flat Major, Op. 53 \"Heroic\"",
      "artist": "Vladimir Ashkenazy",
      "duration_ms": 376000
    },
    {
      "id": "Xdcpxs7wh90",
      "title": "POSTERITY",
      "artist": "Ludwig Goransson",
      "duration_ms": 763000
    },
    {
      "id": "7Cc4UsvNFBU",
      "title": "POWERLESS",
      "artist": "Linkin Park",
      "duration_ms": 225000
    },
    {
      "id": "h3ffXDfXO_Y",
      "title": "Priyyotamaa",
      "artist": "Rupankar",
      "duration_ms": 269000
    },
    {
      "id": "FG7MWTz_H4k",
      "title": "THE PROTAGONIST",
      "artist": "Ludwig Goransson",
      "duration_ms": 289000
    },
    {
      "id": "Ld5LCN4Ex6U",
      "title": "Purano Sei Diner Kotha",
      "artist": "Release",
      "duration_ms": 237000
    },
    {
      "id": "Z25GNhpajyY",
      "title": "Qayde Se",
      "artist": "Arijit Singh",
      "duration_ms": 216000
    },
    {
      "id": "jzfJrEwYYHs",
      "title": "The Queen's Justice",
      "artist": "Ramin Djawadi",
      "duration_ms": 82000
    },
    {
      "id": "piUHBTXsoiY",
      "title": "Raabta",
      "artist": "Arijit Singh",
      "duration_ms": 244000
    },
    {
      "id": "sudXI02WdPM",
      "title": "Radioactive",
      "artist": "ImagineDragons",
      "duration_ms": 187000
    },
    {
      "id": "USNr_n-NYmc",
      "title": "The Rains of Castamere",
      "artist": "Ramin Djawadi",
      "duration_ms": 225000
    },
    {
      "id": "H7c-YbQIFlw",
      "title": "The Rains of Castamere from Game of Thrones",
      "artist": "Tina Guo",
      "duration_ms": 168000
    },
    {
      "id": "OcKSsXs0FA4",
      "title": "Rap God",
      "artist": "EminemMusic",
      "duration_ms": 364000
    },
    {
      "id": "YsC-rkK3H3o",
      "title": "Rasputin (Single Version)",
      "artist": "Boney M.",
      "duration_ms": 221000
    },
    {
      "id": "CjUVTEExfBg",
      "title": "The Real Folk Blues",
      "artist": "Mai Yamane",
      "duration_ms": 378000
    },
    {
      "id": "r5MR7_INQwg",
      "title": "The Real Slim Shady",
      "artist": "EminemMusic",
      "duration_ms": 285000
    },
    {
      "id": "VYYqDDHcjpc",
      "title": "Red",
      "artist": "Daniel Lanois",
      "duration_ms": 136000
    },
    {
      "id": "44mxIJOO-ZQ",
      "title": "The Red Woman",
      "artist": "Ramin Djawadi",
      "duration_ms": 198000
    },
    {
      "id": "sSvWOba4H1I",
      "title": "Reign",
      "artist": "Ramin Djawadi",
      "duration_ms": 197000
    },
    {
      "id": "bNoWHflgLRs",
      "title": "Requiem for a Dream",
      "artist": "Scott Benson Band",
      "duration_ms": 298000
    },
    {
      "id": "57krkMHJQDg",
      "title": "Returning",
      "artist": "Gustavo Santaolalla",
      "duration_ms": 216000
    },
    {
      "id": "iaeeZLnrFbA",
      "title": "Right Round",
      "artist": "Flo Rida",
      "duration_ms": 205000
    },
    {
      "id": "c504EGCwQlU",
      "title": "Rishte Naate",
      "artist": "The Folk \u0026 Soul Studio",
      "duration_ms": 275000
    },
    {
      "id": "Nqh4Z8nfyDs",
      "title": "ROADS UNTRAVELED",
      "artist": "Linkin Park",
      "duration_ms": 230000
    },
    {
      "id": "wqpv0qgJEbU",
      "title": "Roopkathara (Male)",
      "artist": "Rupankar Bagchi",
      "duration_ms": 348000
    },
    {
      "id": "KHCIO7a3jSI",
      "title": "The Rumbling (TV Size)",
      "artist": "SiM Official YouTube Channel",
      "duration_ms": 91000
    },
    {
      "id": "MU3EOO4fWQo",
      "title": "S.T.A.Y.",
      "artist": "Hans Zimmer",
      "duration_ms": 384000
    },
    {
      "id": "jZCrERNYsBY",
      "title": "Saibo",
      "artist": "Sachin Jigar",
      "duration_ms": 196000
    },
    {
      "id": "nLfhkoB4D5k",
      "title": "Sail",
      "artist": "AWOLNATION",
      "duration_ms": 260000
    },
    {
      "id": "pqBKTLnowdM",
      "title": "Saiyyan",
      "artist": "Kailash Kher",
      "duration_ms": 344000
    },
    {
      "id": "9hzqvAiKCZQ",
      "title": "Sajani Sajani",
      "artist": "Manomay Bhattacharya",
      "duration_ms": 256000
    },
    {
      "id": "cjS-XIU5ypA",
      "title": "Sandese Aate Hai (From \"Border\")",
      "artist": "Roopkumar Rathod (Official)",
      "duration_ms": 633000
    },
    {
      "id": "xT-5e1F1p8Y",
      "title": "Sapphire",
      "artist": "Ed Sheeran",
      "duration_ms": 180000
    },
    {
      "id": "RmYCOm4ehKs",
      "title": "Save Your Tears",
      "artist": "The Weeknd",
      "duration_ms": 216000
    },
    {
      "id": "wIUXC9fxAt8",
      "title": "School road",
      "artist": "RADWIMPS",
      "duration_ms": 69000
    },
    {
      "id": "gm-Y9idMMQ4",
      "title": "The Scientist",
      "artist": "Coldplay",
      "duration_ms": 310000
    },
    {
      "id": "Xr1qIqtnziI",
      "title": "Sea of Dreams",
      "artist": "Oberhofer",
      "duration_ms": 284000
    },
    {
      "id": "s8QTDOm8UE4",
      "title": "Sea of Dreams (From \"BoJack Horseman\")",
      "artist": "Alex Heflin",
      "duration_ms": 276000
    },
    {
      "id": "4YNaaX0-nbI",
      "title": "See You Again (feat. Charlie Puth)",
      "artist": "Wiz Khalifa",
      "duration_ms": 230000
    },
    {
      "id": "TuzmJDfv_IM",
      "title": "See You for What You Are",
      "artist": "Ramin Djawadi",
      "duration_ms": 130000
    },
    {
      "id": "VKC_hzJ3jzg",
      "title": "Señorita",
      "artist": "Shawn Mendes",
      "duration_ms": 191000
    },
    {
      "id": "W8Y1Qh8SbEw",
      "title": "Setsuko and Seita",
      "artist": "Roma Symphony Orchestra",
      "duration_ms": 157000
    },
    {
      "id": "D_QLxj8jCF0",
      "title": "Seven Nation Army",
      "artist": "The White Stripes",
      "duration_ms": 233000
    },
    {
      "id": "3RVfdaxPTd8",
      "title": "Seven Nation Army",
      "artist": "2CELLOS",
      "duration_ms": 160000
    },
    {
      "id": "rct1x6VjEZ4",
      "title": "Shall We Begin?",
      "artist": "Ramin Djawadi",
      "duration_ms": 85000
    },
    {
      "id": "vnt65_GElMU",
      "title": "Shauq",
      "artist": "Amit Trivedi",
      "duration_ms": 257000
    },
    {
      "id": "9onQEY15mOs",
      "title": "Sheher Mein",
      "artist": "Mohit Chauhan",
      "duration_ms": 242000
    },
    {
      "id": "IzaXlq1Pdmk",
      "title": "Shelter from the Storm",
      "artist": "Bob Dylan",
      "duration_ms": 302000
    },
    {
      "id": "RPf0vW_xTrc",
      "title": "Shohage Adore (From \"Belashuru\")",
      "artist": "Anupam Roy",
      "duration_ms": 334000
    },
    {
      "id": "MJNGXnvHYPg",
      "title": "Sing For The Moment",
      "artist": "EminemMusic",
      "duration_ms": 340000
    },
    {
      "id": "IRL7Refc2oM",
      "title": "SKIN TO BONE",
      "artist": "Linkin Park",
      "duration_ms": 169000
    },
    {
      "id": "LJzp_mDxaT0",
      "title": "Skyfall",
      "artist": "Adele",
      "duration_ms": 287000
    },
    {
      "id": "wkJTd_wKl0k",
      "title": "Smooth Criminal (2012 Remaster)",
      "artist": "Michael Jackson",
      "duration_ms": 258000
    },
    {
      "id": "OPgmQc3OkFs",
      "title": "Smooth Operator",
      "artist": "Sade",
      "duration_ms": 299000
    },
    {
      "id": "OQ86YrcW-s4",
      "title": "Sochta Hoon Keh Woh Kitne Masoom The",
      "artist": "Nusrat Fateh Ali Khan",
      "duration_ms": 1373000
    },
    {
      "id": "0agQX9O_pKc",
      "title": "Sokhi Bhabona Kahare Bole",
      "artist": "Somlata Acharyya Chowdhury",
      "duration_ms": 244000
    },
    {
      "id": "xOazTYPrt64",
      "title": "Somebody That I Used To Know",
      "artist": "Gotye",
      "duration_ms": 245000
    },
    {
      "id": "SVSjcS-N224",
      "title": "Something In The Way",
      "artist": "Nirvana",
      "duration_ms": 233000
    },
    {
      "id": "PkjaBCLOAec",
      "title": "Something Just Like This",
      "artist": "The Chainsmokers",
      "duration_ms": 248000
    },
    {
      "id": "7cn3aQL9O9I",
      "title": "Somewhere Only We Know",
      "artist": "Keane",
      "duration_ms": 236000
    },
    {
      "id": "Wa1NpajBJ6U",
      "title": "Son of the Harpy",
      "artist": "Ramin Djawadi",
      "duration_ms": 318000
    },
    {
      "id": "57QKAe5ALW8",
      "title": "Beethoven: Violin Sonata No. 9 in A Major, Op. 47 \"Kreutzer\": I. Adagio sostenuto – Presto",
      "artist": "Henryk Szeryng",
      "duration_ms": 734000
    },
    {
      "id": "ItJlq9uQSQo",
      "title": "A Song of Ice and Fire",
      "artist": "Ramin Djawadi",
      "duration_ms": 132000
    },
    {
      "id": "H-UeNnrQBF4",
      "title": "Soona Man Ka Aangan",
      "artist": "Sonu Nigam",
      "duration_ms": 264000
    },
    {
      "id": "93TW692tQb8",
      "title": "Soviet Connection (Theme from GTA IV)",
      "artist": "Michael Hunter",
      "duration_ms": 172000
    },
    {
      "id": "-J9FuvPmMoI",
      "title": "Sparkle - movie ver.",
      "artist": "RADWIMPS",
      "duration_ms": 538000
    },
    {
      "id": "JpbJXflNXvI",
      "title": "Spinnin",
      "artist": "Connor Price",
      "duration_ms": 111000
    },
    {
      "id": "eU_pT3SKUCc",
      "title": "Spoils of War, Pt. 1",
      "artist": "Ramin Djawadi",
      "duration_ms": 234000
    },
    {
      "id": "h1aqWceMz4E",
      "title": "Spoils of War, Pt. 2",
      "artist": "Ramin Djawadi",
      "duration_ms": 244000
    },
    {
      "id": "X791IzOwt3Q",
      "title": "Stairway to Heaven (Remaster)",
      "artist": "Led Zeppelin",
      "duration_ms": 486000
    },
    {
      "id": "HIqQ0PfuPo8",
      "title": "Stan",
      "artist": "EminemMusic",
      "duration_ms": 405000
    },
    {
      "id": "l1J1hJpwRAQ",
      "title": "Stand by Me",
      "artist": "Ben E. King",
      "duration_ms": 181000
    },
    {
      "id": "3_g2un5M350",
      "title": "Starboy",
      "artist": "The Weeknd",
      "duration_ms": 231000
    },
    {
      "id": "zVbldiNLalo",
      "title": "Stay",
      "artist": "Hans Zimmer",
      "duration_ms": 413000
    },
    {
      "id": "vOIeXBEKeLc",
      "title": "Stayin Alive",
      "artist": "beegees",
      "duration_ms": 286000
    },
    {
      "id": "qflJJO3V6aE",
      "title": "Still Alive",
      "artist": "Aperture Science Psychoacoustic Laboratories",
      "duration_ms": 178000
    },
    {
      "id": "Qeem6ZVr8Ic",
      "title": "Still D.R.E.",
      "artist": "Dr. Dre",
      "duration_ms": 271000
    },
    {
      "id": "2ulp_AMut14",
      "title": "Stronger",
      "artist": "Kanye West",
      "duration_ms": 312000
    },
    {
      "id": "MpG_ft84IoE",
      "title": "Sucker (from the series Arcane League of Legends)",
      "artist": "Marcus King ",
      "duration_ms": 225000
    },
    {
      "id": "bjnoBceY1NE",
      "title": "Summer Of '69",
      "artist": "Bryan Adams",
      "duration_ms": 217000
    },
    {
      "id": "K_8yRH2KPVo",
      "title": "Superman",
      "artist": "EminemMusic",
      "duration_ms": 351000
    },
    {
      "id": "9LW9DpmhrPE",
      "title": "Suzume (feat. Toaka)",
      "artist": "RADWIMPS",
      "duration_ms": 237000
    },
    {
      "id": "fov74iW1Kv4",
      "title": "Sway",
      "artist": "Michael Bublé",
      "duration_ms": 189000
    },
    {
      "id": "ubcapZQYA1U",
      "title": "Sweet Disposition",
      "artist": "The Temper Trap",
      "duration_ms": 237000
    },
    {
      "id": "eRhg7qPLeN8",
      "title": "Sweet Dreams (Are Made of This) (2005 Remaster)",
      "artist": "Eurythmics",
      "duration_ms": 217000
    },
    {
      "id": "zCj_U2nc_Hk",
      "title": "Taakey Olpo Kachhe Dakchhi",
      "artist": "Mahtim Shakib",
      "duration_ms": 195000
    },
    {
      "id": "-YT-PUXH_yI",
      "title": "Tadap Tadap",
      "artist": "KK",
      "duration_ms": 396000
    },
    {
      "id": "PY7r-px554Y",
      "title": "Take Me Down Easy",
      "artist": "James Henry Jr.",
      "duration_ms": 249000
    },
    {
      "id": "idkdKeXaC3M",
      "title": "Talking to Myself",
      "artist": "Linkin Park",
      "duration_ms": 232000
    },
    {
      "id": "uzgomxS85Fo",
      "title": "Tango pour Claude",
      "artist": "Richard Galliano",
      "duration_ms": 250000
    },
    {
      "id": "UFFa0QoHWvE",
      "title": "Tank!",
      "artist": "Seatbelts",
      "duration_ms": 211000
    },
    {
      "id": "AkfRIaiZmdo",
      "title": "Tara Jwele",
      "artist": "Lagnajita Chakraborty",
      "duration_ms": 174000
    },
    {
      "id": "Wrq7VsjSPWM",
      "title": "Targaryen Theme (Epic Version)",
      "artist": "Samuel Kim Music",
      "duration_ms": 225000
    },
    {
      "id": "i1WW3FOvBWo",
      "title": "Teeth",
      "artist": "5SOS",
      "duration_ms": 206000
    },
    {
      "id": "VzXPGIFDde8",
      "title": "Tera Deedar Hua",
      "artist": "Pritam",
      "duration_ms": 348000
    },
    {
      "id": "oeYgD5w3NQo",
      "title": "Tera Hone Laga Hoon",
      "artist": "Pritam",
      "duration_ms": 300000
    },
    {
      "id": "DtaWY_FXyeM",
      "title": "Tere Naina",
      "artist": "Shankar Ehsaan Loy",
      "duration_ms": 279000
    }
  ],
  "current": 1
}