{
  "boostName": "x",
  "dotAngleDeg": 91.91489361702126,
  "dotPos": {
    "x": 0.8321652140455564,
    "y": 0.4528139789972735
  },
  "dotDistance": 1.0,
  "secondaryDotAngleDegDelta": 314.2389525368249,
  "secondaryDotPos": {
    "x": 0.6979300501277577,
    "y": 0.2291052875074463
  },
  "brightness": 0.6840958605664488,
  "saturation": 0.5786206896551723,
  "contrast": "0.63",
  "fontFamily": "Inter Display",
  "enableColorBoost": true,
  "smartInvert": false,
  "autoTheme": false,
  "textCaseOverride": "none",
  "sizeOverride": 1,
  "zapSelectors": [
    "nav.css-175oi2r.r-eqz5dr.r-13qz1uu.r-1habvwh > a.css-175oi2r.r-6koalj.r-eqz5dr.r-16y2uox.r-1habvwh.r-cnw61z.r-13qz1uu.r-1ny4l3l.r-1loqt21:nth-child(8)",
    "body:last-child > div#react-root:nth-child(2) > div.css-175oi2r.r-13awgt0.r-12vffkv:first-child > div.css-175oi2r.r-13awgt0.r-12vffkv:first-child > div#layers.r-zchlnj.r-1d2f490.r-u8s1d.r-ipm5af:nth-child(2) > div.css-175oi2r.r-aqfbo4.r-zchlnj.r-1d2f490.r-1xcajam.r-1p0dtai.r-12vffkv:first-child > div.css-175oi2r.r-12vffkv:first-child > div.css-175oi2r.r-12vffkv:first-child > div.css-175oi2r.r-633pao.r-173mn98.r-6gpygo.r-1va2g9v.r-bnwqim > button.css-175oi2r.r-105ug2t.r-1awozwy.r-173mn98.r-1e5uvyk.r-5zmot.r-j7xza8.r-1867qdf.r-rs99b7.r-qo02w8.r-8oi148.r-1777fci.r-u8s1d.r-1tfmumk.r-1loqt21.r-o7ynqc.r-6416eg.r-1ny4l3l:first-child",
    "div.css-175oi2r.r-633pao.r-173mn98.r-6koalj.r-1euycsn.r-6gpygo.r-1va2g9v.r-bnwqim > button.css-175oi2r.r-105ug2t.r-1awozwy.r-173mn98.r-1e5uvyk.r-5zmot.r-j7xza8.r-1867qdf.r-rs99b7.r-qo02w8.r-8oi148.r-1777fci.r-u8s1d.r-1tfmumk.r-1loqt21.r-o7ynqc.r-6416eg.r-1ny4l3l:first-child",
    "div.css-175oi2r.r-kemksi.r-1kqtdi0.r-1867qdf.r-1phboty.r-rs99b7.r-1ifxtd0.r-1udh08x > aside.css-175oi2r.r-1habvwh.r-eqz5dr.r-uaa2di.r-w7s2jr.r-u9wvl5.r-bnwqim:first-child"
  ],
  "changeWasMade": true,
  "customCSS": "/* .r-1gn8etr {\n  position: sticky !important;\n  top: -50px !important;\n} */\n\n/* div.css-175oi2r.r-vacyoi.r-ttdzmv, div.css-175oi2r.r-1pi2tsx.r-1wtj0ep.r-1rnoaur.r-o96wvk.r-is05cd {\n  opacity: 0 !important;\n  transition: all 0.3s ease-in-out !important;\n  &:hover {\n    opacity: 1 !important;\n  }\n} */\n\n@media (min-width: 1200px) {\n\n  header[role=\"banner\"] {\n    width: 0px !important;\n  }\n\n  .r-1ye8kvj {\n    max-width: 900px !important;\n  }\n}\n\n/*transparent*/\nhtml, body, [data-testid=\"primaryColumn\"], .r-kemksi:has([aria-live=\"polite\"]), [aria-label=\"Home timeline\"] .r-5zmot, [aria-label=\"Grok\"] .r-5zmot, article, div.r-1hycxz:nth-child(1), div.r-1ifxtd0:nth-child(1), div.r-kemksi:nth-child(4), div.r-kemksi:nth-child(5), [data-testid=\"cellInnerDiv\"] > div, [aria-label=\"Home timeline\"] > div > div > div > div > div > div, [aria-label=\"Section navigation\"] [role=\"tablist\"] > div, [aria-label=\"Section navigation\"] > div, [aria-label=\"Section navigation\"] > div > div > div > div, [aria-label=\"Section details\"] [role=\"tablist\"] > div, [aria-label=\"Section details\"] > div, [aria-label=\"Section details\"] > div > div > div > div, [data-testid=\"inline_reply_offscreen\"] > div, .css-175oi2r.r-kemksi.r-jumn1c.r-xd6kpl.r-gtdqiz.r-ipm5af.r-184en5c {\n  background-color: transparent !important;\n  background: none !important;\n  border: none !important;\n  box-shadow: none !important;\n}\n[data-testid=\"Dropdown\"], .css-175oi2r[role=\"dialog\"], div.r-ifefl9:nth-child(2) {\n  background-color: #fff !important;\n\n  @media (prefers-color-scheme: dark) {\n    background-color: #000 !important;\n  }\n}\n/*end*/"
}